{"samples":1000,"simulations":[{"t1":0,"w1":0,"x1":0,"nq1":3528.9,"t2":0.000275272,"w2":1.92725e-05,"x2":0.000256,"nq2":0.000420068,"jitterE":0.0159993,"jitterV":1.05806e-10},{"t1":0,"w1":0,"x1":0,"nq1":3576.29,"t2":0.000265545,"w2":9.54495e-06,"x2":0.000256,"nq2":0.000219131,"jitterE":0.0160007,"jitterV":3.74103e-10,"confidenceInterval":{"t1":{"lesser":0,"mean":0,"upper":0,"percentage":0},"w1":{"lesser":0,"mean":0,"upper":0,"percentage":0},"x1":{"lesser":0,"mean":0,"upper":0,"percentage":0},"nq1":{"lesser":1243.28,"mean":7105.18,"upper":12967.1,"percentage":165.004},"t2":{"lesser":9.45709e-05,"mean":0.000540817,"upper":0.000987064,"percentage":165.027},"w2":{"lesser":-0.000161429,"mean":0.000284817,"upper":0.000731064,"percentage":313.356},"nq2":{"lesser":8.64176e-05,"mean":0.000639199,"upper":0.00119198,"percentage":172.961},"jitterMean":{"lesser":0.00560001,"mean":0.032,"upper":0.0584001,"percentage":165},"jitterVariance":{"lesser":2.6312e-11,"mean":4.79909e-10,"upper":9.33506e-10,"percentage":189.035}}},{"t1":0,"w1":0,"x1":0,"nq1":3627.15,"t2":0.000271231,"w2":1.52309e-05,"x2":0.000256,"nq2":0.000277494,"jitterE":0.0160004,"jitterV":3.95414e-10,"confidenceInterval":{"t1":{"lesser":0,"mean":0,"upper":0,"percentage":0},"w1":{"lesser":0,"mean":0,"upper":0,"percentage":0},"x1":{"lesser":0,"mean":0,"upper":0,"percentage":0},"nq1":{"lesser":2384.41,"mean":10732.3,"upper":19080.3,"percentage":155.566},"t2":{"lesser":0.000180406,"mean":0.000812048,"upper":0.00144369,"percentage":155.568},"w2":{"lesser":-7.55942e-05,"mean":0.000556048,"upper":0.00118769,"percentage":227.19},"nq2":{"lesser":0.000196906,"mean":0.000916693,"upper":0.00163648,"percentage":157.04},"jitterMean":{"lesser":0.0106649,"mean":0.0480004,"upper":0.085336,"percentage":155.563},"jitterVariance":{"lesser":1.77335e-10,"mean":8.75323e-10,"upper":1.57331e-09,"percentage":159.481}}},{"t1":0,"w1":0,"x1":0,"nq1":3679.41,"t2":0.000288743,"w2":3.27434e-05,"x2":0.000256,"nq2":0.000893029,"jitterE":0.0159988,"jitterV":6.51171e-10,"confidenceInterval":{"t1":{"lesser":0,"mean":0,"upper":0,"percentage":0},"w1":{"lesser":0,"mean":0,"upper":0,"percentage":0},"x1":{"lesser":0,"mean":0,"upper":0,"percentage":0},"nq1":{"lesser":4114.83,"mean":14411.7,"upper":24708.6,"percentage":142.896},"t2":{"lesser":0.000314266,"mean":0.00110079,"upper":0.00188732,"percentage":142.902},"w2":{"lesser":5.82659e-05,"mean":0.000844792,"upper":0.00163132,"percentage":186.206},"nq2":{"lesser":0.000492374,"mean":0.00180972,"upper":0.00312707,"percentage":145.586},"jitterMean":{"lesser":0.0182736,"mean":0.0639992,"upper":0.109725,"percentage":142.894},"jitterVariance":{"lesser":4.20472e-10,"mean":1.52649e-09,"upper":2.63252e-09,"percentage":144.91}}},{"t1":0,"w1":0,"x1":0,"nq1":3737.65,"t2":0.00027974,"w2":2.37405e-05,"x2":0.000256,"nq2":0.000597576,"jitterE":0.0160001,"jitterV":3.84515e-10,"confidenceInterval":{"t1":{"lesser":0,"mean":0,"upper":0,"percentage":0},"w1":{"lesser":0,"mean":0,"upper":0,"percentage":0},"x1":{"lesser":0,"mean":0,"upper":0,"percentage":0},"nq1":{"lesser":6170.64,"mean":18149.4,"upper":30128.1,"percentage":132.002},"t2":{"lesser":0.000469358,"mean":0.00138053,"upper":0.00229171,"percentage":132.003},"w2":{"lesser":0.000213358,"mean":0.00112453,"upper":0.00203571,"percentage":162.054},"nq2":{"lesser":0.000805806,"mean":0.0024073,"upper":0.00400879,"percentage":133.053},"jitterMean":{"lesser":0.0271998,"mean":0.0799994,"upper":0.132799,"percentage":132},"jitterVariance":{"lesser":6.41729e-10,"mean":1.91101e-09,"upper":3.18029e-09,"percentage":132.839}}},{"t1":0,"w1":0,"x1":0,"nq1":3827.49,"t2":0.000272616,"w2":1.66164e-05,"x2":0.000256,"nq2":0.000308802,"jitterE":0.0159994,"jitterV":3.69691e-10,"confidenceInterval":{"t1":{"lesser":0,"mean":0,"upper":0,"percentage":0},"w1":{"lesser":0,"mean":0,"upper":0,"percentage":0},"x1":{"lesser":0,"mean":0,"upper":0,"percentage":0},"nq1":{"lesser":8462.68,"mean":21976.9,"upper":35491.1,"percentage":122.986},"t2":{"lesser":0.000636582,"mean":0.00165315,"upper":0.00266971,"percentage":122.985},"w2":{"lesser":0.000380582,"mean":0.00139715,"upper":0.00241371,"percentage":145.52},"nq2":{"lesser":0.0010372,"mean":0.0027161,"upper":0.004395,"percentage":123.626},"jitterMean":{"lesser":0.0369673,"mean":0.0959988,"upper":0.15503,"percentage":122.984},"jitterVariance":{"lesser":8.73439e-10,"mean":2.2807e-09,"upper":3.68796e-09,"percentage":123.406}}},{"t1":0,"w1":0,"x1":0,"nq1":3883.46,"t2":0.000295687,"w2":3.96868e-05,"x2":0.000256,"nq2":0.000895463,"jitterE":0.0160008,"jitterV":2.32789e-10,"confidenceInterval":{"t1":{"lesser":0,"mean":0,"upper":0,"percentage":0},"w1":{"lesser":0,"mean":0,"upper":0,"percentage":0},"x1":{"lesser":0,"mean":0,"upper":0,"percentage":0},"nq1":{"lesser":10928.9,"mean":25860.3,"upper":40791.8,"percentage":115.478},"t2":{"lesser":0.000823598,"mean":0.00194884,"upper":0.00307407,"percentage":115.478},"w2":{"lesser":0.000567598,"mean":0.00169284,"upper":0.00281807,"percentage":132.941},"nq2":{"lesser":0.00151872,"mean":0.00361156,"upper":0.00570441,"percentage":115.897},"jitterMean":{"lesser":0.0473333,"mean":0.112,"upper":0.176666,"percentage":115.476},"jitterVariance":{"lesser":1.05851e-09,"mean":2.51349e-09,"upper":3.96847e-09,"percentage":115.774}}},{"t1":0,"w1":0,"x1":0,"nq1":3925.14,"t2":0.000288445,"w2":3.24452e-05,"x2":0.000256,"nq2":0.000683687,"jitterE":0.0160002,"jitterV":3.82627e-10,"confidenceInterval":{"t1":{"lesser":0,"mean":0,"upper":0,"percentage":0},"w1":{"lesser":0,"mean":0,"upper":0,"percentage":0},"x1":{"lesser":0,"mean":0,"upper":0,"percentage":0},"nq1":{"lesser":13531.7,"mean":29785.5,"upper":46039.2,"percentage":109.139},"t2":{"lesser":0.00101641,"mean":0.00223728,"upper":0.00345815,"percentage":109.139},"w2":{"lesser":0.000760412,"mean":0.00198128,"upper":0.00320215,"percentage":123.24},"nq2":{"lesser":0.00194606,"mean":0.00429525,"upper":0.00664444,"percentage":109.385},"jitterMean":{"lesser":0.058152,"mean":0.128,"upper":0.197847,"percentage":109.137},"jitterVariance":{"lesser":1.31316e-09,"mean":2.89612e-09,"upper":4.47907e-09,"percentage":109.316}}},{"t1":0,"w1":0,"x1":0,"nq1":3937.93,"t2":0.000272471,"w2":1.64714e-05,"x2":0.000256,"nq2":0.000311197,"jitterE":0.0159999,"jitterV":4.36911e-10,"confidenceInterval":{"t1":{"lesser":0,"mean":0,"upper":0,"percentage":0},"w1":{"lesser":0,"mean":0,"upper":0,"percentage":0},"x1":{"lesser":0,"mean":0,"upper":0,"percentage":0},"nq1":{"lesser":16236.1,"mean":33723.4,"upper":51210.7,"percentage":103.71},"t2":{"lesser":0.00120832,"mean":0.00250975,"upper":0.00381118,"percentage":103.71},"w2":{"lesser":0.000952321,"mean":0.00225375,"upper":0.00355518,"percentage":115.49},"nq2":{"lesser":0.00221337,"mean":0.00460645,"upper":0.00699953,"percentage":103.901},"jitterMean":{"lesser":0.0693293,"mean":0.144,"upper":0.21867,"percentage":103.709},"jitterVariance":{"lesser":1.60281e-09,"mean":3.33303e-09,"upper":5.06325e-09,"percentage":103.823}}},{"t1":0,"w1":0,"x1":0,"nq1":4007.23,"t2":0.000287521,"w2":3.15213e-05,"x2":0.000256,"nq2":0.000872804,"jitterE":0.0160003,"jitterV":4.24019e-10,"confidenceInterval":{"t1":{"lesser":0,"mean":0,"upper":0,"percentage":0},"w1":{"lesser":0,"mean":0,"upper":0,"percentage":0},"x1":{"lesser":0,"mean":0,"upper":0,"percentage":0},"nq1":{"lesser":19053.8,"mean":37730.6,"upper":56407.5,"percentage":99.0011},"t2":{"lesser":0.00141261,"mean":0.00279727,"upper":0.00418193,"percentage":99.0007},"w2":{"lesser":0.00115661,"mean":0.00254127,"upper":0.00392593,"percentage":108.974},"nq2":{"lesser":0.00276325,"mean":0.00547925,"upper":0.00819525,"percentage":99.1377},"jitterMean":{"lesser":0.0808,"mean":0.16,"upper":0.2392,"percentage":99},"jitterVariance":{"lesser":1.89588e-09,"mean":3.75705e-09,"upper":5.61821e-09,"percentage":99.0761}}},{"t1":0,"w1":0,"x1":0,"nq1":4083.5,"t2":0.000291311,"w2":3.5311e-05,"x2":0.000256,"nq2":0.000884483,"jitterE":0.0160007,"jitterV":6.33789e-10,"confidenceInterval":{"t1":{"lesser":0,"mean":0,"upper":0,"percentage":0},"w1":{"lesser":0,"mean":0,"upper":0,"percentage":0},"x1":{"lesser":0,"mean":0,"upper":0,"percentage":0},"nq1":{"lesser":21979.7,"mean":41814.1,"upper":61648.5,"percentage":94.8693},"t2":{"lesser":0.00162353,"mean":0.00308858,"upper":0.00455364,"percentage":94.8689},"w2":{"lesser":0.00136753,"mean":0.00283258,"upper":0.00429764,"percentage":103.443},"nq2":{"lesser":0.00334195,"mean":0.00636373,"upper":0.00938552,"percentage":94.9688},"jitterMean":{"lesser":0.0925162,"mean":0.176001,"upper":0.259485,"percentage":94.8683},"jitterVariance":{"lesser":2.30668e-09,"mean":4.39083e-09,"upper":6.47499e-09,"percentage":94.9323}}},{"t1":0,"w1":0,"x1":0,"nq1":4140.79,"t2":0.000283346,"w2":2.73464e-05,"x2":0.000256,"nq2":0.000659486,"jitterE":0.0159998,"jitterV":9.14929e-10,"confidenceInterval":{"t1":{"lesser":0,"mean":0,"upper":0,"percentage":0},"w1":{"lesser":0,"mean":0,"upper":0,"percentage":0},"x1":{"lesser":0,"mean":0,"upper":0,"percentage":0},"nq1":{"lesser":24997.6,"mean":45954.9,"upper":66912.2,"percentage":91.2081},"t2":{"lesser":0.0018342,"mean":0.00337193,"upper":0.00490966,"percentage":91.2076},"w2":{"lesser":0.0015782,"mean":0.00311593,"upper":0.00465366,"percentage":98.701},"nq2":{"lesser":0.00381785,"mean":0.00702322,"upper":0.0102286,"percentage":91.2792},"jitterMean":{"lesser":0.104441,"mean":0.192,"upper":0.27956,"percentage":91.2072},"jitterVariance":{"lesser":2.8841e-09,"mean":5.30576e-09,"upper":7.72743e-09,"percentage":91.2843}}},{"t1":0,"w1":0,"x1":0,"nq1":4191.34,"t2":0.000273523,"w2":1.75229e-05,"x2":0.000256,"nq2":0.000323332,"jitterE":0.0160012,"jitterV":5.77147e-10,"confidenceInterval":{"t1":{"lesser":0,"mean":0,"upper":0,"percentage":0},"w1":{"lesser":0,"mean":0,"upper":0,"percentage":0},"x1":{"lesser":0,"mean":0,"upper":0,"percentage":0},"nq1":{"lesser":28098,"mean":50146.3,"upper":72194.5,"percentage":87.9358},"t2":{"lesser":0.00204264,"mean":0.00364545,"upper":0.00524827,"percentage":87.9352},"w2":{"lesser":0.00178664,"mean":0.00338945,"upper":0.00499227,"percentage":94.5768},"nq2":{"lesser":0.00411417,"mean":0.00734655,"upper":0.0105789,"percentage":87.9973},"jitterMean":{"lesser":0.116549,"mean":0.208002,"upper":0.299455,"percentage":87.9349},"jitterVariance":{"lesser":3.29467e-09,"mean":5.88291e-09,"upper":8.47115e-09,"percentage":87.9919}}},{"t1":0,"w1":0,"x1":0,"nq1":4201.79,"t2":0.000285642,"w2":2.96424e-05,"x2":0.000256,"nq2":0.000540098,"jitterE":0.0159997,"jitterV":8.87804e-10,"confidenceInterval":{"t1":{"lesser":0,"mean":0,"upper":0,"percentage":0},"w1":{"lesser":0,"mean":0,"upper":0,"percentage":0},"x1":{"lesser":0,"mean":0,"upper":0,"percentage":0},"nq1":{"lesser":31253.2,"mean":54348.1,"upper":77443,"percentage":84.9888},"t2":{"lesser":0.00226061,"mean":0.0039311,"upper":0.00560158,"percentage":84.9882},"w2":{"lesser":0.00200461,"mean":0.0036751,"upper":0.00534558,"percentage":90.9084},"nq2":{"lesser":0.0045334,"mean":0.00788665,"upper":0.0112399,"percentage":85.0361},"jitterMean":{"lesser":0.128814,"mean":0.224001,"upper":0.319188,"percentage":84.988},"jitterVariance":{"lesser":3.89182e-09,"mean":6.77071e-09,"upper":9.64961e-09,"percentage":85.0397}}},{"t1":0,"w1":0,"x1":0,"nq1":4236.3,"t2":0.000301369,"w2":4.5369e-05,"x2":0.000256,"nq2":0.000986978,"jitterE":0.0160009,"jitterV":1.32204e-09,"confidenceInterval":{"t1":{"lesser":0,"mean":0,"upper":0,"percentage":0},"w1":{"lesser":0,"mean":0,"upper":0,"percentage":0},"x1":{"lesser":0,"mean":0,"upper":0,"percentage":0},"nq1":{"lesser":34471.9,"mean":58584.4,"upper":82696.9,"percentage":82.3172},"t2":{"lesser":0.00249045,"mean":0.00423247,"upper":0.00597448,"percentage":82.3167},"w2":{"lesser":0.00223445,"mean":0.00397647,"upper":0.00571848,"percentage":87.6162},"nq2":{"lesser":0.00521959,"mean":0.00887363,"upper":0.0125277,"percentage":82.3572},"jitterMean":{"lesser":0.141222,"mean":0.240002,"upper":0.338783,"percentage":82.3165},"jitterVariance":{"lesser":4.75934e-09,"mean":8.09276e-09,"upper":1.14262e-08,"percentage":82.3804}}},{"t1":0,"w1":0,"x1":0,"nq1":4286.64,"t2":0.00029781,"w2":4.18103e-05,"x2":0.000256,"nq2":0.00085558,"jitterE":0.0159995,"jitterV":6.22794e-10,"confidenceInterval":{"t1":{"lesser":0,"mean":0,"upper":0,"percentage":0},"w1":{"lesser":0,"mean":0,"upper":0,"percentage":0},"x1":{"lesser":0,"mean":0,"upper":0,"percentage":0},"nq1":{"lesser":37760,"mean":62871,"upper":87982,"percentage":79.8809},"t2":{"lesser":0.00272087,"mean":0.00453028,"upper":0.00633968,"percentage":79.8805},"w2":{"lesser":0.00246487,"mean":0.00427428,"upper":0.00608368,"percentage":84.6648},"nq2":{"lesser":0.00584177,"mean":0.00972921,"upper":0.0136166,"percentage":79.9128},"jitterMean":{"lesser":0.153754,"mean":0.256002,"upper":0.358249,"percentage":79.8803},"jitterVariance":{"lesser":5.23237e-09,"mean":8.71555e-09,"upper":1.21987e-08,"percentage":79.9302}}},{"t1":0,"w1":0,"x1":0,"nq1":4318.66,"t2":0.000277875,"w2":2.18749e-05,"x2":0.000256,"nq2":0.000505974,"jitterE":0.0160004,"jitterV":1.61586e-10,"confidenceInterval":{"t1":{"lesser":0,"mean":0,"upper":0,"percentage":0},"w1":{"lesser":0,"mean":0,"upper":0,"percentage":0},"x1":{"lesser":0,"mean":0,"upper":0,"percentage":0},"nq1":{"lesser":41104.1,"mean":67189.7,"upper":93275.3,"percentage":77.6477},"t2":{"lesser":0.00294145,"mean":0.00480815,"upper":0.00667485,"percentage":77.6473},"w2":{"lesser":0.00268545,"mean":0.00455215,"upper":0.00641885,"percentage":82.0139},"nq2":{"lesser":0.00626015,"mean":0.0102352,"upper":0.0142102,"percentage":77.6739},"jitterMean":{"lesser":0.166401,"mean":0.272002,"upper":0.377603,"percentage":77.6471},"jitterVariance":{"lesser":5.42858e-09,"mean":8.87714e-09,"upper":1.23257e-08,"percentage":77.6953}}},{"t1":0,"w1":0,"x1":0,"nq1":4388.82,"t2":0.000268378,"w2":1.23778e-05,"x2":0.000256,"nq2":0.000286141,"jitterE":0.0160004,"jitterV":2.37124e-10,"confidenceInterval":{"t1":{"lesser":0,"mean":0,"upper":0,"percentage":0},"w1":{"lesser":0,"mean":0,"upper":0,"percentage":0},"x1":{"lesser":0,"mean":0,"upper":0,"percentage":0},"nq1":{"lesser":44525.1,"mean":71578.5,"upper":98631.9,"percentage":75.5908},"t2":{"lesser":0.00315784,"mean":0.00507653,"upper":0.00699521,"percentage":75.5904},"w2":{"lesser":0.00290184,"mean":0.00482053,"upper":0.00673921,"percentage":79.6048},"nq2":{"lesser":0.00654345,"mean":0.0105213,"upper":0.0144992,"percentage":75.6155},"jitterMean":{"lesser":0.179152,"mean":0.288003,"upper":0.396854,"percentage":75.5903},"jitterVariance":{"lesser":5.66751e-09,"mean":9.11426e-09,"upper":1.2561e-08,"percentage":75.6342}}},{"t1":0,"w1":0,"x1":0,"nq1":4447.81,"t2":0.000265843,"w2":9.84275e-06,"x2":0.000256,"nq2":0.00026504,"jitterE":0.0159998,"jitterV":1.47151e-10,"confidenceInterval":{"t1":{"lesser":0,"mean":0,"upper":0,"percentage":0},"w1":{"lesser":0,"mean":0,"upper":0,"percentage":0},"x1":{"lesser":0,"mean":0,"upper":0,"percentage":0},"nq1":{"lesser":48015,"mean":76026.3,"upper":104038,"percentage":73.6885},"t2":{"lesser":0.00337402,"mean":0.00534237,"upper":0.00731072,"percentage":73.6881},"w2":{"lesser":0.00311802,"mean":0.00508637,"upper":0.00705472,"percentage":77.3969},"nq2":{"lesser":0.00681095,"mean":0.0107864,"upper":0.0147618,"percentage":73.7118},"jitterMean":{"lesser":0.191996,"mean":0.304002,"upper":0.416009,"percentage":73.688},"jitterVariance":{"lesser":5.84719e-09,"mean":9.26141e-09,"upper":1.26756e-08,"percentage":73.7301}}},{"t1":0,"w1":0,"x1":0,"nq1":4526.46,"t2":0.000287809,"w2":3.18091e-05,"x2":0.000256,"nq2":0.000759599,"jitterE":0.0160004,"jitterV":7.74025e-10,"confidenceInterval":{"t1":{"lesser":0,"mean":0,"upper":0,"percentage":0},"w1":{"lesser":0,"mean":0,"upper":0,"percentage":0},"x1":{"lesser":0,"mean":0,"upper":0,"percentage":0},"nq1":{"lesser":51585,"mean":80552.8,"upper":109520,"percentage":71.9224},"t2":{"lesser":0.00360551,"mean":0.00563018,"upper":0.00765485,"percentage":71.922},"w2":{"lesser":0.00334951,"mean":0.00537418,"upper":0.00739885,"percentage":75.348},"nq2":{"lesser":0.00739279,"mean":0.011546,"upper":0.0156991,"percentage":71.9415},"jitterMean":{"lesser":0.204927,"mean":0.320003,"upper":0.435079,"percentage":71.9218},"jitterVariance":{"lesser":6.42487e-09,"mean":1.00354e-08,"upper":1.3646e-08,"percentage":71.9565}}},{"t1":0,"w1":0,"x1":0,"nq1":4591.39,"t2":0.000278667,"w2":2.26669e-05,"x2":0.000256,"nq2":0.000497147,"jitterE":0.0159985,"jitterV":4.52368e-10,"confidenceInterval":{"t1":{"lesser":0,"mean":0,"upper":0,"percentage":0},"w1":{"lesser":0,"mean":0,"upper":0,"percentage":0},"x1":{"lesser":0,"mean":0,"upper":0,"percentage":0},"nq1":{"lesser":55225.8,"mean":85144.2,"upper":115063,"percentage":70.2769},"t2":{"lesser":0.00383258,"mean":0.00590885,"upper":0.00798511,"percentage":70.2765},"w2":{"lesser":0.00357658,"mean":0.00565285,"upper":0.00772911,"percentage":73.4591},"nq2":{"lesser":0.00781036,"mean":0.0120431,"upper":0.0162759,"percentage":70.2933},"jitterMean":{"lesser":0.217936,"mean":0.336001,"upper":0.454066,"percentage":70.2764},"jitterVariance":{"lesser":6.80104e-09,"mean":1.04878e-08,"upper":1.41746e-08,"percentage":70.3058}}},{"t1":0,"w1":0,"x1":0,"nq1":4669.55,"t2":0.000279546,"w2":2.35463e-05,"x2":0.000256,"nq2":0.000424089,"jitterE":0.0159996,"jitterV":1.3263e-10,"confidenceInterval":{"t1":{"lesser":0,"mean":0,"upper":0,"percentage":0},"w1":{"lesser":0,"mean":0,"upper":0,"percentage":0},"x1":{"lesser":0,"mean":0,"upper":0,"percentage":0},"nq1":{"lesser":58945.1,"mean":89813.7,"upper":120682,"percentage":68.7391},"t2":{"lesser":0.00406148,"mean":0.00618839,"upper":0.00831531,"percentage":68.7387},"w2":{"lesser":0.00380548,"mean":0.00593239,"upper":0.00805931,"percentage":71.705},"nq2":{"lesser":0.00818138,"mean":0.0124672,"upper":0.016753,"percentage":68.7535},"jitterMean":{"lesser":0.231021,"mean":0.352001,"upper":0.472981,"percentage":68.7386},"jitterVariance":{"lesser":6.96875e-09,"mean":1.06204e-08,"upper":1.42721e-08,"percentage":68.7672}}},{"t1":0,"w1":0,"x1":0,"nq1":4742.26,"t2":0.000304583,"w2":4.85826e-05,"x2":0.000256,"nq2":0.0011137,"jitterE":0.0160008,"jitterV":4.55434e-10,"confidenceInterval":{"t1":{"lesser":0,"mean":0,"upper":0,"percentage":0},"w1":{"lesser":0,"mean":0,"upper":0,"percentage":0},"x1":{"lesser":0,"mean":0,"upper":0,"percentage":0},"nq1":{"lesser":62738.9,"mean":94556,"upper":126373,"percentage":67.2978},"t2":{"lesser":0.00430817,"mean":0.00649298,"upper":0.00867778,"percentage":67.2974},"w2":{"lesser":0.00405217,"mean":0.00623698,"upper":0.00842178,"percentage":70.0596},"nq2":{"lesser":0.00901015,"mean":0.0135809,"upper":0.0181516,"percentage":67.3114},"jitterMean":{"lesser":0.244174,"mean":0.368002,"upper":0.491829,"percentage":67.2973},"jitterVariance":{"lesser":7.34763e-09,"mean":1.10759e-08,"upper":1.48041e-08,"percentage":67.3218}}},{"t1":0,"w1":0,"x1":0,"nq1":4800.16,"t2":0.000273113,"w2":1.71132e-05,"x2":0.000256,"nq2":0.00025712,"jitterE":0.0159988,"jitterV":5.3517e-10,"confidenceInterval":{"t1":{"lesser":0,"mean":0,"upper":0,"percentage":0},"w1":{"lesser":0,"mean":0,"upper":0,"percentage":0},"x1":{"lesser":0,"mean":0,"upper":0,"percentage":0},"nq1":{"lesser":66596.8,"mean":99356.1,"upper":132115,"percentage":65.9432},"t2":{"lesser":0.00453522,"mean":0.00676609,"upper":0.00899696,"percentage":65.9428},"w2":{"lesser":0.00427922,"mean":0.00651009,"upper":0.00874096,"percentage":68.5359},"nq2":{"lesser":0.0092745,"mean":0.013838,"upper":0.0184015,"percentage":65.9563},"jitterMean":{"lesser":0.25739,"mean":0.384001,"upper":0.510611,"percentage":65.9427},"jitterVariance":{"lesser":7.78151e-09,"mean":1.1611e-08,"upper":1.54406e-08,"percentage":65.9636}}},{"t1":0,"w1":0,"x1":0,"nq1":4827.31,"t2":0.000277083,"w2":2.10826e-05,"x2":0.000256,"nq2":0.000473767,"jitterE":0.0159998,"jitterV":5.03596e-10,"confidenceInterval":{"t1":{"lesser":0,"mean":0,"upper":0,"percentage":0},"w1":{"lesser":0,"mean":0,"upper":0,"percentage":0},"x1":{"lesser":0,"mean":0,"upper":0,"percentage":0},"nq1":{"lesser":70497.3,"mean":104183,"upper":137870,"percentage":64.667},"t2":{"lesser":0.00476588,"mean":0.00704317,"upper":0.00932046,"percentage":64.6666},"w2":{"lesser":0.00450988,"mean":0.00678717,"upper":0.00906446,"percentage":67.1057},"nq2":{"lesser":0.00968346,"mean":0.0143118,"upper":0.0189401,"percentage":64.6785},"jitterMean":{"lesser":0.270667,"mean":0.4,"upper":0.529333,"percentage":64.6665},"jitterVariance":{"lesser":8.19649e-09,"mean":1.21146e-08,"upper":1.60328e-08,"percentage":64.6846}}},{"t1":0,"w1":0,"x1":0,"nq1":4916.75,"t2":0.000328793,"w2":7.27925e-05,"x2":0.000256,"nq2":0.0018943,"jitterE":0.0160005,"jitterV":8.94116e-10,"confidenceInterval":{"t1":{"lesser":0,"mean":0,"upper":0,"percentage":0},"w1":{"lesser":0,"mean":0,"upper":0,"percentage":0},"x1":{"lesser":0,"mean":0,"upper":0,"percentage":0},"nq1":{"lesser":74481.6,"mean":109100,"upper":143719,"percentage":63.462},"t2":{"lesser":0.00503278,"mean":0.00737196,"upper":0.00971115,"percentage":63.4617},"w2":{"lesser":0.00477678,"mean":0.00711596,"upper":0.00945515,"percentage":65.7447},"nq2":{"lesser":0.0110624,"mean":0.0162061,"upper":0.0213498,"percentage":63.4788},"jitterMean":{"lesser":0.284001,"mean":0.416001,"upper":0.548001,"percentage":63.4615},"jitterVariance":{"lesser":8.87994e-09,"mean":1.30088e-08,"upper":1.71376e-08,"percentage":63.4775}}},{"t1":0,"w1":0,"x1":0,"nq1":4979.93,"t2":0.000279691,"w2":2.36906e-05,"x2":0.000256,"nq2":0.000466217,"jitterE":0.0160004,"jitterV":3.68469e-10,"confidenceInterval":{"t1":{"lesser":0,"mean":0,"upper":0,"percentage":0},"w1":{"lesser":0,"mean":0,"upper":0,"percentage":0},"x1":{"lesser":0,"mean":0,"upper":0,"percentage":0},"nq1":{"lesser":78531.7,"mean":114080,"upper":149628,"percentage":62.3218},"t2":{"lesser":0.00526734,"mean":0.00765165,"upper":0.010036,"percentage":62.3215},"w2":{"lesser":0.00501134,"mean":0.00739565,"upper":0.00977997,"percentage":64.4787},"nq2":{"lesser":0.0114758,"mean":0.0166723,"upper":0.0218688,"percentage":62.3368},"jitterMean":{"lesser":0.297387,"mean":0.432001,"upper":0.566616,"percentage":62.3213},"jitterVariance":{"lesser":9.20783e-09,"mean":1.33772e-08,"upper":1.75466e-08,"percentage":62.3357}}},{"t1":0,"w1":0,"x1":0,"nq1":5059.17,"t2":0.000284711,"w2":2.8711e-05,"x2":0.000256,"nq2":0.000663836,"jitterE":0.0160012,"jitterV":4.02789e-10,"confidenceInterval":{"t1":{"lesser":0,"mean":0,"upper":0,"percentage":0},"w1":{"lesser":0,"mean":0,"upper":0,"percentage":0},"x1":{"lesser":0,"mean":0,"upper":0,"percentage":0},"nq1":{"lesser":82658.3,"mean":119139,"upper":155620,"percentage":61.2408},"t2":{"lesser":0.00550623,"mean":0.00793637,"upper":0.0103665,"percentage":61.2405},"w2":{"lesser":0.00525023,"mean":0.00768037,"upper":0.0101105,"percentage":63.2817},"nq2":{"lesser":0.0120266,"mean":0.0173361,"upper":0.0226457,"percentage":61.2539},"jitterMean":{"lesser":0.310823,"mean":0.448002,"upper":0.585182,"percentage":61.2404},"jitterVariance":{"lesser":9.55966e-09,"mean":1.378e-08,"upper":1.80004e-08,"percentage":61.2532}}},{"t1":0,"w1":0,"x1":0,"nq1":5095.27,"t2":0.000266342,"w2":1.03421e-05,"x2":0.000256,"nq2":0.000203197,"jitterE":0.0159999,"jitterV":1.73982e-10,"confidenceInterval":{"t1":{"lesser":0,"mean":0,"upper":0,"percentage":0},"w1":{"lesser":0,"mean":0,"upper":0,"percentage":0},"x1":{"lesser":0,"mean":0,"upper":0,"percentage":0},"nq1":{"lesser":86831.2,"mean":124235,"upper":161638,"percentage":60.2141},"t2":{"lesser":0.00573313,"mean":0.00820271,"upper":0.0106723,"percentage":60.2137},"w2":{"lesser":0.00547713,"mean":0.00794671,"upper":0.0104163,"percentage":62.1535},"nq2":{"lesser":0.0122576,"mean":0.0175393,"upper":0.022821,"percentage":60.2268},"jitterMean":{"lesser":0.324306,"mean":0.464002,"upper":0.603699,"percentage":60.2137},"jitterVariance":{"lesser":9.75202e-09,"mean":1.3954e-08,"upper":1.8156e-08,"percentage":60.2261}}},{"t1":0,"w1":0,"x1":0,"nq1":5159.35,"t2":0.000286075,"w2":3.0075e-05,"x2":0.000256,"nq2":0.00083347,"jitterE":0.0159994,"jitterV":4.90024e-10,"confidenceInterval":{"t1":{"lesser":0,"mean":0,"upper":0,"percentage":0},"w1":{"lesser":0,"mean":0,"upper":0,"percentage":0},"x1":{"lesser":0,"mean":0,"upper":0,"percentage":0},"nq1":{"lesser":91069.2,"mean":129394,"upper":167719,"percentage":59.2373},"t2":{"lesser":0.00597454,"mean":0.00848878,"upper":0.011003,"percentage":59.2369},"w2":{"lesser":0.00571854,"mean":0.00823278,"upper":0.010747,"percentage":61.0789},"nq2":{"lesser":0.01293,"mean":0.0183728,"upper":0.0238156,"percentage":59.2483},"jitterMean":{"lesser":0.337833,"mean":0.480002,"upper":0.62217,"percentage":59.2368},"jitterVariance":{"lesser":1.01651e-08,"mean":1.4444e-08,"upper":1.87229e-08,"percentage":59.2478}}}],"average":{"t1":0,"w1":0,"x1":0,"nq1":4313.13,"t2":0.000282959,"w2":2.69594e-05,"x2":0.000256,"nq2":0.000612427,"jitterE":0.0160001,"jitterV":4.81467e-10},"confidenceInterval":{"t1":{"lesser":0,"mean":0,"upper":0,"percentage":0},"w1":{"lesser":0,"mean":0,"upper":0,"percentage":0},"x1":{"lesser":0,"mean":0,"upper":0,"percentage":0},"nq1":{"lesser":4165.8,"mean":4313.13,"upper":4460.45,"percentage":6.83146},"t2":{"lesser":0.000278893,"mean":0.000282959,"upper":0.000287026,"percentage":2.87405},"w2":{"lesser":2.28932e-05,"mean":2.69594e-05,"upper":3.10256e-05,"percentage":30.1653},"nq2":{"lesser":0.000505226,"mean":0.000612427,"upper":0.000719628,"percentage":35.0085},"jitterMean":{"lesser":0.0159998,"mean":0.0160001,"upper":0.0160003,"percentage":0.00262951},"jitterVariance":{"lesser":3.99074e-10,"mean":4.81467e-10,"upper":5.6386e-10,"percentage":34.2259}}}
