{"samples":100,"simulations":[{"t1":0,"w1":0,"x1":0,"nq1":10430.1,"t2":0.000286585,"w2":3.05851e-05,"x2":0.000256,"nq2":0.0010451,"jitterE":0.016,"jitterV":-4.95635e-19},{"t1":0,"w1":0,"x1":0,"nq1":10443.1,"t2":0.000291394,"w2":3.53943e-05,"x2":0.000256,"nq2":0.000871555,"jitterE":0.0160027,"jitterV":5.90987e-10,"confidenceInterval":{"t1":{"lesser":0,"mean":0,"upper":0,"percentage":0},"w1":{"lesser":0,"mean":0,"upper":0,"percentage":0},"x1":{"lesser":0,"mean":0,"upper":0,"percentage":0},"nq1":{"lesser":10417.6,"mean":10436.6,"upper":10455.5,"percentage":0.362837},"t2":{"lesser":0.000281968,"mean":0.00028899,"upper":0.000296011,"percentage":4.8593},"w2":{"lesser":2.59682e-05,"mean":3.29897e-05,"upper":4.00111e-05,"percentage":42.5675},"nq2":{"lesser":0.000704949,"mean":0.000958328,"upper":0.00121171,"percentage":52.8793},"jitterMean":{"lesser":0.0159974,"mean":0.0160014,"upper":0.0160054,"percentage":0.0499116},"jitterVariance":{"lesser":-5.67347e-10,"mean":2.95493e-10,"upper":1.15833e-09,"percentage":584}}},{"t1":0,"w1":0,"x1":0,"nq1":10461.7,"t2":0.000288707,"w2":3.2707e-05,"x2":0.000256,"nq2":0.000689513,"jitterE":0.016,"jitterV":-3.19554e-19,"confidenceInterval":{"t1":{"lesser":0,"mean":0,"upper":0,"percentage":0},"w1":{"lesser":0,"mean":0,"upper":0,"percentage":0},"x1":{"lesser":0,"mean":0,"upper":0,"percentage":0},"nq1":{"lesser":10423.4,"mean":10444.9,"upper":10466.5,"percentage":0.413236},"t2":{"lesser":0.000285621,"mean":0.000288895,"upper":0.00029217,"percentage":2.26669},"w2":{"lesser":2.96213e-05,"mean":3.28954e-05,"upper":3.61696e-05,"percentage":19.9066},"nq2":{"lesser":0.000627165,"mean":0.000868723,"upper":0.00111028,"percentage":55.6122},"jitterMean":{"lesser":0.0159988,"mean":0.0160009,"upper":0.0160031,"percentage":0.026814},"jitterVariance":{"lesser":-2.66535e-10,"mean":1.96996e-10,"upper":6.60526e-10,"percentage":470.6}}},{"t1":0,"w1":0,"x1":0,"nq1":10483.1,"t2":0.000282904,"w2":2.69044e-05,"x2":0.000256,"nq2":0.000400412,"jitterE":0.0160014,"jitterV":1.28773e-10,"confidenceInterval":{"t1":{"lesser":0,"mean":0,"upper":0,"percentage":0},"w1":{"lesser":0,"mean":0,"upper":0,"percentage":0},"x1":{"lesser":0,"mean":0,"upper":0,"percentage":0},"nq1":{"lesser":10429.9,"mean":10454.5,"upper":10479.1,"percentage":0.470564},"t2":{"lesser":0.000283577,"mean":0.000287398,"upper":0.000291218,"percentage":2.65877},"w2":{"lesser":2.75771e-05,"mean":3.13977e-05,"upper":3.52183e-05,"percentage":24.3369},"nq2":{"lesser":0.00045795,"mean":0.000751645,"upper":0.00104534,"percentage":78.1473},"jitterMean":{"lesser":0.0159996,"mean":0.016001,"upper":0.0160024,"percentage":0.017468},"jitterVariance":{"lesser":-1.19259e-10,"mean":1.7994e-10,"upper":4.79139e-10,"percentage":332.554}}},{"t1":0,"w1":0,"x1":0,"nq1":10504.2,"t2":0.00026124,"w2":5.23951e-06,"x2":0.000256,"nq2":0.000100292,"jitterE":0.0159984,"jitterV":2.56364e-10,"confidenceInterval":{"t1":{"lesser":0,"mean":0,"upper":0,"percentage":0},"w1":{"lesser":0,"mean":0,"upper":0,"percentage":0},"x1":{"lesser":0,"mean":0,"upper":0,"percentage":0},"nq1":{"lesser":10437.5,"mean":10464.4,"upper":10491.4,"percentage":0.514942},"t2":{"lesser":0.00027126,"mean":0.000282166,"upper":0.000293073,"percentage":7.73056},"w2":{"lesser":1.52595e-05,"mean":2.61661e-05,"upper":3.70726e-05,"percentage":83.3638},"nq2":{"lesser":0.000282062,"mean":0.000621375,"upper":0.000960688,"percentage":109.214},"jitterMean":{"lesser":0.015999,"mean":0.0160005,"upper":0.016002,"percentage":0.0182912},"jitterVariance":{"lesser":-2.59699e-11,"mean":1.95225e-10,"upper":4.1642e-10,"percentage":226.605}}},{"t1":0,"w1":0,"x1":0,"nq1":10524.1,"t2":0.000268459,"w2":1.24588e-05,"x2":0.000256,"nq2":0.00024391,"jitterE":0.016,"jitterV":-2.89121e-19,"confidenceInterval":{"t1":{"lesser":0,"mean":0,"upper":0,"percentage":0},"w1":{"lesser":0,"mean":0,"upper":0,"percentage":0},"x1":{"lesser":0,"mean":0,"upper":0,"percentage":0},"nq1":{"lesser":10445.7,"mean":10474.4,"upper":10503.1,"percentage":0.547752},"t2":{"lesser":0.000270215,"mean":0.000279882,"upper":0.000289548,"percentage":6.90747},"w2":{"lesser":1.42151e-05,"mean":2.38815e-05,"upper":3.35479e-05,"percentage":80.9527},"nq2":{"lesser":0.000264679,"mean":0.000558464,"upper":0.000852249,"percentage":105.212},"jitterMean":{"lesser":0.0159993,"mean":0.0160004,"upper":0.0160016,"percentage":0.014549},"jitterVariance":{"lesser":-2.25841e-11,"mean":1.62687e-10,"upper":3.47959e-10,"percentage":227.764}}},{"t1":0,"w1":0,"x1":0,"nq1":10543.6,"t2":0.000267905,"w2":1.19053e-05,"x2":0.000256,"nq2":0.000250455,"jitterE":0.0159975,"jitterV":2.2969e-10,"confidenceInterval":{"t1":{"lesser":0,"mean":0,"upper":0,"percentage":0},"w1":{"lesser":0,"mean":0,"upper":0,"percentage":0},"x1":{"lesser":0,"mean":0,"upper":0,"percentage":0},"nq1":{"lesser":10454.1,"mean":10484.3,"upper":10514.4,"percentage":0.575718},"t2":{"lesser":0.000269569,"mean":0.000278171,"upper":0.000286773,"percentage":6.18478},"w2":{"lesser":1.35685e-05,"mean":2.21706e-05,"upper":3.07728e-05,"percentage":77.5993},"nq2":{"lesser":0.000258349,"mean":0.000514463,"upper":0.000770576,"percentage":99.5655},"jitterMean":{"lesser":0.0159988,"mean":0.016,"upper":0.0160013,"percentage":0.0154982},"jitterVariance":{"lesser":1.84711e-11,"mean":1.72259e-10,"upper":3.26047e-10,"percentage":178.554}}},{"t1":0,"w1":0,"x1":0,"nq1":10548.7,"t2":0.000256,"w2":-6.84939e-15,"x2":0.000256,"nq2":0,"jitterE":0.016,"jitterV":-2.93193e-19,"confidenceInterval":{"t1":{"lesser":0,"mean":0,"upper":0,"percentage":0},"w1":{"lesser":0,"mean":0,"upper":0,"percentage":0},"x1":{"lesser":0,"mean":0,"upper":0,"percentage":0},"nq1":{"lesser":10462.6,"mean":10492.3,"upper":10522,"percentage":0.566338},"t2":{"lesser":0.000266453,"mean":0.000275399,"upper":0.000284346,"percentage":6.49699},"w2":{"lesser":1.0453e-05,"mean":1.93993e-05,"upper":2.83456e-05,"percentage":92.2336},"nq2":{"lesser":0.000201755,"mean":0.000450155,"upper":0.000698554,"percentage":110.362},"jitterMean":{"lesser":0.015999,"mean":0.016,"upper":0.0160011,"percentage":0.013174},"jitterVariance":{"lesser":1.40047e-11,"mean":1.50727e-10,"upper":2.87449e-10,"percentage":181.417}}},{"t1":0,"w1":0,"x1":0,"nq1":10557.6,"t2":0.000293862,"w2":3.78622e-05,"x2":0.000256,"nq2":0.000531685,"jitterE":0.0160054,"jitterV":1.15662e-09,"confidenceInterval":{"t1":{"lesser":0,"mean":0,"upper":0,"percentage":0},"w1":{"lesser":0,"mean":0,"upper":0,"percentage":0},"x1":{"lesser":0,"mean":0,"upper":0,"percentage":0},"nq1":{"lesser":10470.5,"mean":10499.6,"upper":10528.6,"percentage":0.553229},"t2":{"lesser":0.000268814,"mean":0.000277451,"upper":0.000286088,"percentage":6.22592},"w2":{"lesser":1.28138e-05,"mean":2.14507e-05,"upper":3.00877e-05,"percentage":80.528},"nq2":{"lesser":0.000242688,"mean":0.000459214,"upper":0.000675739,"percentage":94.3027},"jitterMean":{"lesser":0.0159992,"mean":0.0160006,"upper":0.016002,"percentage":0.0178115},"jitterVariance":{"lesser":2.56587e-11,"mean":2.62493e-10,"upper":4.99326e-10,"percentage":180.45}}},{"t1":0,"w1":0,"x1":0,"nq1":10559.1,"t2":0.000299347,"w2":4.33471e-05,"x2":0.000256,"nq2":0.000949796,"jitterE":0.0159992,"jitterV":5.20664e-11,"confidenceInterval":{"t1":{"lesser":0,"mean":0,"upper":0,"percentage":0},"w1":{"lesser":0,"mean":0,"upper":0,"percentage":0},"x1":{"lesser":0,"mean":0,"upper":0,"percentage":0},"nq1":{"lesser":10477.7,"mean":10505.5,"upper":10533.4,"percentage":0.530234},"t2":{"lesser":0.000271035,"mean":0.00027964,"upper":0.000288246,"percentage":6.1549},"w2":{"lesser":1.50346e-05,"mean":2.36404e-05,"upper":3.22462e-05,"percentage":72.8059},"nq2":{"lesser":0.000297193,"mean":0.000508272,"upper":0.000719351,"percentage":83.0573},"jitterMean":{"lesser":0.0159992,"mean":0.0160005,"upper":0.0160018,"percentage":0.016068},"jitterVariance":{"lesser":2.86031e-11,"mean":2.4145e-10,"upper":4.54297e-10,"percentage":176.307}}},{"t1":0,"w1":0,"x1":0,"nq1":10566.7,"t2":0.000297411,"w2":4.14112e-05,"x2":0.000256,"nq2":0.000815681,"jitterE":0.0159993,"jitterV":9.97029e-10,"confidenceInterval":{"t1":{"lesser":0,"mean":0,"upper":0,"percentage":0},"w1":{"lesser":0,"mean":0,"upper":0,"percentage":0},"x1":{"lesser":0,"mean":0,"upper":0,"percentage":0},"nq1":{"lesser":10484.2,"mean":10511.1,"upper":10538,"percentage":0.511683},"t2":{"lesser":0.000273013,"mean":0.000281256,"upper":0.000289499,"percentage":5.86159},"w2":{"lesser":1.70129e-05,"mean":2.52559e-05,"upper":3.34989e-05,"percentage":65.2761},"nq2":{"lesser":0.000340434,"mean":0.000536218,"upper":0.000732003,"percentage":73.0243},"jitterMean":{"lesser":0.0159992,"mean":0.0160004,"upper":0.0160015,"percentage":0.0146027},"jitterVariance":{"lesser":8.29077e-11,"mean":3.10139e-10,"upper":5.3737e-10,"percentage":146.535}}},{"t1":0,"w1":0,"x1":0,"nq1":10573.4,"t2":0.000282909,"w2":2.69089e-05,"x2":0.000256,"nq2":0.000550289,"jitterE":0.0160011,"jitterV":6.82444e-11,"confidenceInterval":{"t1":{"lesser":0,"mean":0,"upper":0,"percentage":0},"w1":{"lesser":0,"mean":0,"upper":0,"percentage":0},"x1":{"lesser":0,"mean":0,"upper":0,"percentage":0},"nq1":{"lesser":10490.2,"mean":10516.3,"upper":10542.3,"percentage":0.495524},"t2":{"lesser":0.000273923,"mean":0.000281394,"upper":0.000288864,"percentage":5.30943},"w2":{"lesser":1.79235e-05,"mean":2.53937e-05,"upper":3.28639e-05,"percentage":58.8352},"nq2":{"lesser":0.000360045,"mean":0.000537391,"upper":0.000714736,"percentage":66.0024},"jitterMean":{"lesser":0.0159994,"mean":0.0160004,"upper":0.0160015,"percentage":0.0132897},"jitterVariance":{"lesser":8.1054e-11,"mean":2.89981e-10,"upper":4.98908e-10,"percentage":144.097}}},{"t1":0,"w1":0,"x1":0,"nq1":10589.8,"t2":0.000273231,"w2":1.72314e-05,"x2":0.000256,"nq2":0.00047131,"jitterE":0.0159967,"jitterV":8.40205e-10,"confidenceInterval":{"t1":{"lesser":0,"mean":0,"upper":0,"percentage":0},"w1":{"lesser":0,"mean":0,"upper":0,"percentage":0},"x1":{"lesser":0,"mean":0,"upper":0,"percentage":0},"nq1":{"lesser":10496.1,"mean":10521.9,"upper":10547.8,"percentage":0.491185},"t2":{"lesser":0.000273847,"mean":0.000280766,"upper":0.000287685,"percentage":4.92874},"w2":{"lesser":1.78467e-05,"mean":2.47658e-05,"upper":3.16849e-05,"percentage":55.8763},"nq2":{"lesser":0.000369931,"mean":0.000532308,"upper":0.000694684,"percentage":61.0086},"jitterMean":{"lesser":0.015999,"mean":0.0160001,"upper":0.0160012,"percentage":0.013685},"jitterVariance":{"lesser":1.27125e-10,"mean":3.32306e-10,"upper":5.37487e-10,"percentage":123.489}}},{"t1":0,"w1":0,"x1":0,"nq1":10603.6,"t2":0.000256259,"w2":2.59451e-07,"x2":0.000256,"nq2":1.26812e-05,"jitterE":0.0159997,"jitterV":6.0043e-12,"confidenceInterval":{"t1":{"lesser":0,"mean":0,"upper":0,"percentage":0},"w1":{"lesser":0,"mean":0,"upper":0,"percentage":0},"x1":{"lesser":0,"mean":0,"upper":0,"percentage":0},"nq1":{"lesser":10501.9,"mean":10527.8,"upper":10553.7,"percentage":0.492259},"t2":{"lesser":0.000271939,"mean":0.000279015,"upper":0.000286092,"percentage":5.07238},"w2":{"lesser":1.5939e-05,"mean":2.30153e-05,"upper":3.00917e-05,"percentage":61.4925},"nq2":{"lesser":0.000332044,"mean":0.000495192,"upper":0.000658339,"percentage":65.8929},"jitterMean":{"lesser":0.0159991,"mean":0.0160001,"upper":0.0160011,"percentage":0.0126143},"jitterVariance":{"lesser":1.15703e-10,"mean":3.08999e-10,"upper":5.02294e-10,"percentage":125.111}}},{"t1":0,"w1":0,"x1":0,"nq1":10620.3,"t2":0.000257325,"w2":1.32498e-06,"x2":0.000256,"nq2":0,"jitterE":0.016,"jitterV":-3.19554e-19,"confidenceInterval":{"t1":{"lesser":0,"mean":0,"upper":0,"percentage":0},"w1":{"lesser":0,"mean":0,"upper":0,"percentage":0},"x1":{"lesser":0,"mean":0,"upper":0,"percentage":0},"nq1":{"lesser":10507.6,"mean":10533.9,"upper":10560.3,"percentage":0.500059},"t2":{"lesser":0.000270539,"mean":0.000277569,"upper":0.0002846,"percentage":5.06589},"w2":{"lesser":1.45386e-05,"mean":2.15693e-05,"upper":2.86e-05,"percentage":65.1915},"nq2":{"lesser":0.000300289,"mean":0.000462179,"upper":0.000624068,"percentage":70.055},"jitterMean":{"lesser":0.0159992,"mean":0.0160001,"upper":0.016001,"percentage":0.0116909},"jitterVariance":{"lesser":1.05664e-10,"mean":2.88399e-10,"upper":4.71134e-10,"percentage":126.724}}},{"t1":0,"w1":0,"x1":0,"nq1":10639.1,"t2":0.000257568,"w2":1.56807e-06,"x2":0.000256,"nq2":3.80352e-05,"jitterE":0.015998,"jitterV":3.13421e-10,"confidenceInterval":{"t1":{"lesser":0,"mean":0,"upper":0,"percentage":0},"w1":{"lesser":0,"mean":0,"upper":0,"percentage":0},"x1":{"lesser":0,"mean":0,"upper":0,"percentage":0},"nq1":{"lesser":10513.4,"mean":10540.5,"upper":10567.6,"percentage":0.513962},"t2":{"lesser":0.000269415,"mean":0.000276319,"upper":0.000283224,"percentage":4.99741},"w2":{"lesser":1.34148e-05,"mean":2.03192e-05,"upper":2.72236e-05,"percentage":67.9593},"nq2":{"lesser":0.000277899,"mean":0.00043567,"upper":0.000593441,"percentage":72.4269},"jitterMean":{"lesser":0.0159991,"mean":0.016,"upper":0.0160009,"percentage":0.01125},"jitterVariance":{"lesser":1.19691e-10,"mean":2.89963e-10,"upper":4.60235e-10,"percentage":117.444}}},{"t1":0,"w1":0,"x1":0,"nq1":10658.9,"t2":0.000273796,"w2":1.7796e-05,"x2":0.000256,"nq2":0.000267109,"jitterE":0.016,"jitterV":-2.89121e-19,"confidenceInterval":{"t1":{"lesser":0,"mean":0,"upper":0,"percentage":0},"w1":{"lesser":0,"mean":0,"upper":0,"percentage":0},"x1":{"lesser":0,"mean":0,"upper":0,"percentage":0},"nq1":{"lesser":10519.4,"mean":10547.5,"upper":10575.6,"percentage":0.53291},"t2":{"lesser":0.000269702,"mean":0.000276171,"upper":0.000282639,"percentage":4.68437},"w2":{"lesser":1.37024e-05,"mean":2.01708e-05,"upper":2.66392e-05,"percentage":64.1365},"nq2":{"lesser":0.000277059,"mean":0.000425754,"upper":0.00057445,"percentage":69.8502},"jitterMean":{"lesser":0.0159991,"mean":0.016,"upper":0.0160008,"percentage":0.0105313},"jitterVariance":{"lesser":1.10774e-10,"mean":2.72906e-10,"upper":4.35039e-10,"percentage":118.819}}},{"t1":0,"w1":0,"x1":0,"nq1":10668.2,"t2":0.000290647,"w2":3.46469e-05,"x2":0.000256,"nq2":0.00077567,"jitterE":0.0159983,"jitterV":2.22065e-10,"confidenceInterval":{"t1":{"lesser":0,"mean":0,"upper":0,"percentage":0},"w1":{"lesser":0,"mean":0,"upper":0,"percentage":0},"x1":{"lesser":0,"mean":0,"upper":0,"percentage":0},"nq1":{"lesser":10525.3,"mean":10554.2,"upper":10583,"percentage":0.546785},"t2":{"lesser":0.00027074,"mean":0.000276975,"upper":0.00028321,"percentage":4.5025},"w2":{"lesser":1.47396e-05,"mean":2.0975e-05,"upper":2.72104e-05,"percentage":59.4555},"nq2":{"lesser":0.000301477,"mean":0.000445194,"upper":0.000588911,"percentage":64.5636},"jitterMean":{"lesser":0.0159991,"mean":0.0159999,"upper":0.0160007,"percentage":0.0100889},"jitterVariance":{"lesser":1.1767e-10,"mean":2.70082e-10,"upper":4.22493e-10,"percentage":112.863}}},{"t1":0,"w1":0,"x1":0,"nq1":10673.3,"t2":0.000282425,"w2":2.64247e-05,"x2":0.000256,"nq2":0.000535146,"jitterE":0.0159985,"jitterV":1.73751e-10,"confidenceInterval":{"t1":{"lesser":0,"mean":0,"upper":0,"percentage":0},"w1":{"lesser":0,"mean":0,"upper":0,"percentage":0},"x1":{"lesser":0,"mean":0,"upper":0,"percentage":0},"nq1":{"lesser":10531.2,"mean":10560.5,"upper":10589.8,"percentage":0.554811},"t2":{"lesser":0.00027136,"mean":0.000277262,"upper":0.000283164,"percentage":4.25732},"w2":{"lesser":1.53599e-05,"mean":2.12619e-05,"upper":2.71638e-05,"percentage":55.5169},"nq2":{"lesser":0.000314131,"mean":0.000449929,"upper":0.000585726,"percentage":60.364},"jitterMean":{"lesser":0.015999,"mean":0.0159998,"upper":0.0160006,"percentage":0.00963592},"jitterVariance":{"lesser":1.20993e-10,"mean":2.65012e-10,"upper":4.0903e-10,"percentage":108.688}}},{"t1":0,"w1":0,"x1":0,"nq1":10689.7,"t2":0.000268045,"w2":1.2045e-05,"x2":0.000256,"nq2":0.000272922,"jitterE":0.016,"jitterV":-4.00321e-19,"confidenceInterval":{"t1":{"lesser":0,"mean":0,"upper":0,"percentage":0},"w1":{"lesser":0,"mean":0,"upper":0,"percentage":0},"x1":{"lesser":0,"mean":0,"upper":0,"percentage":0},"nq1":{"lesser":10537,"mean":10566.9,"upper":10596.8,"percentage":0.565619},"t2":{"lesser":0.000271159,"mean":0.000276801,"upper":0.000282443,"percentage":4.07688},"w2":{"lesser":1.51586e-05,"mean":2.0801e-05,"upper":2.64434e-05,"percentage":54.2514},"nq2":{"lesser":0.000311644,"mean":0.000441078,"upper":0.000570512,"percentage":58.6899},"jitterMean":{"lesser":0.0159991,"mean":0.0159998,"upper":0.0160005,"percentage":0.00912263},"jitterVariance":{"lesser":1.13546e-10,"mean":2.51761e-10,"upper":3.89976e-10,"percentage":109.798}}},{"t1":0,"w1":0,"x1":0,"nq1":10708,"t2":0.0002696,"w2":1.35996e-05,"x2":0.000256,"nq2":0.00025638,"jitterE":0.0160029,"jitterV":6.1027e-10,"confidenceInterval":{"t1":{"lesser":0,"mean":0,"upper":0,"percentage":0},"w1":{"lesser":0,"mean":0,"upper":0,"percentage":0},"x1":{"lesser":0,"mean":0,"upper":0,"percentage":0},"nq1":{"lesser":10543,"mean":10573.6,"upper":10604.3,"percentage":0.579282},"t2":{"lesser":0.000271071,"mean":0.000276458,"upper":0.000281845,"percentage":3.89715},"w2":{"lesser":1.50711e-05,"mean":2.04581e-05,"upper":2.58451e-05,"percentage":52.6637},"nq2":{"lesser":0.000308523,"mean":0.000432283,"upper":0.000556043,"percentage":57.2588},"jitterMean":{"lesser":0.0159992,"mean":0.016,"upper":0.0160007,"percentage":0.00921896},"jitterVariance":{"lesser":1.34419e-10,"mean":2.68833e-10,"upper":4.03247e-10,"percentage":99.9982}}},{"t1":0,"w1":0,"x1":0,"nq1":10726.8,"t2":0.000267304,"w2":1.13037e-05,"x2":0.000256,"nq2":0.000192332,"jitterE":0.0160039,"jitterV":6.58078e-10,"confidenceInterval":{"t1":{"lesser":0,"mean":0,"upper":0,"percentage":0},"w1":{"lesser":0,"mean":0,"upper":0,"percentage":0},"x1":{"lesser":0,"mean":0,"upper":0,"percentage":0},"nq1":{"lesser":10549.1,"mean":10580.6,"upper":10612.1,"percentage":0.595251},"t2":{"lesser":0.000270868,"mean":0.000276042,"upper":0.000281216,"percentage":3.74865},"w2":{"lesser":1.48681e-05,"mean":2.0042e-05,"upper":2.52159e-05,"percentage":51.6309},"nq2":{"lesser":0.00030217,"mean":0.000421376,"upper":0.000540583,"percentage":56.5796},"jitterMean":{"lesser":0.0159994,"mean":0.0160001,"upper":0.0160009,"percentage":0.00958089},"jitterVariance":{"lesser":1.55106e-10,"mean":2.86526e-10,"upper":4.17946e-10,"percentage":91.7336}}},{"t1":0,"w1":0,"x1":0,"nq1":10750.5,"t2":0.00028801,"w2":3.20104e-05,"x2":0.000256,"nq2":0.00059484,"jitterE":0.0160035,"jitterV":4.50273e-10,"confidenceInterval":{"t1":{"lesser":0,"mean":0,"upper":0,"percentage":0},"w1":{"lesser":0,"mean":0,"upper":0,"percentage":0},"x1":{"lesser":0,"mean":0,"upper":0,"percentage":0},"nq1":{"lesser":10555.4,"mean":10588,"upper":10620.6,"percentage":0.615732},"t2":{"lesser":0.000271547,"mean":0.000276562,"upper":0.000281578,"percentage":3.62679},"w2":{"lesser":1.55472e-05,"mean":2.05624e-05,"upper":2.55775e-05,"percentage":48.7801},"nq2":{"lesser":0.000314479,"mean":0.000428918,"upper":0.000543357,"percentage":53.3618},"jitterMean":{"lesser":0.0159995,"mean":0.0160003,"upper":0.0160011,"percentage":0.00967173},"jitterVariance":{"lesser":1.67696e-10,"mean":2.93645e-10,"upper":4.19595e-10,"percentage":85.7834}}},{"t1":0,"w1":0,"x1":0,"nq1":10769.1,"t2":0.000298037,"w2":4.20365e-05,"x2":0.000256,"nq2":0.00100433,"jitterE":0.0160028,"jitterV":6.60762e-10,"confidenceInterval":{"t1":{"lesser":0,"mean":0,"upper":0,"percentage":0},"w1":{"lesser":0,"mean":0,"upper":0,"percentage":0},"x1":{"lesser":0,"mean":0,"upper":0,"percentage":0},"nq1":{"lesser":10561.8,"mean":10595.5,"upper":10629.3,"percentage":0.636598},"t2":{"lesser":0.000272425,"mean":0.000277457,"upper":0.000282489,"percentage":3.62708},"w2":{"lesser":1.64253e-05,"mean":2.14571e-05,"upper":2.64889e-05,"percentage":46.901},"nq2":{"lesser":0.000336078,"mean":0.000452893,"upper":0.000569709,"percentage":51.5861},"jitterMean":{"lesser":0.0159996,"mean":0.0160004,"upper":0.0160012,"percentage":0.00951444},"jitterVariance":{"lesser":1.85753e-10,"mean":3.08942e-10,"upper":4.32131e-10,"percentage":79.7488}}},{"t1":0,"w1":0,"x1":0,"nq1":10787.3,"t2":0.000299889,"w2":4.38887e-05,"x2":0.000256,"nq2":0.00117878,"jitterE":0.0159974,"jitterV":5.23285e-10,"confidenceInterval":{"t1":{"lesser":0,"mean":0,"upper":0,"percentage":0},"w1":{"lesser":0,"mean":0,"upper":0,"percentage":0},"x1":{"lesser":0,"mean":0,"upper":0,"percentage":0},"nq1":{"lesser":10568.4,"mean":10603.2,"upper":10638.1,"percentage":0.657312},"t2":{"lesser":0.000273299,"mean":0.000278354,"upper":0.00028341,"percentage":3.6326},"w2":{"lesser":1.72986e-05,"mean":2.23544e-05,"upper":2.74101e-05,"percentage":45.2327},"nq2":{"lesser":0.000359579,"mean":0.000481929,"upper":0.000604279,"percentage":50.7752},"jitterMean":{"lesser":0.0159995,"mean":0.0160003,"upper":0.016001,"percentage":0.00945319},"jitterVariance":{"lesser":1.98659e-10,"mean":3.17516e-10,"upper":4.36372e-10,"percentage":74.8668}}},{"t1":0,"w1":0,"x1":0,"nq1":10793.5,"t2":0.000291247,"w2":3.52466e-05,"x2":0.000256,"nq2":0.000796943,"jitterE":0.016,"jitterV":-3.60462e-19,"confidenceInterval":{"t1":{"lesser":0,"mean":0,"upper":0,"percentage":0},"w1":{"lesser":0,"mean":0,"upper":0,"percentage":0},"x1":{"lesser":0,"mean":0,"upper":0,"percentage":0},"nq1":{"lesser":10574.8,"mean":10610.5,"upper":10646.2,"percentage":0.672844},"t2":{"lesser":0.000273925,"mean":0.00027885,"upper":0.000283775,"percentage":3.5323},"w2":{"lesser":1.79253e-05,"mean":2.28502e-05,"upper":2.77751e-05,"percentage":43.106},"nq2":{"lesser":0.000374827,"mean":0.000494045,"upper":0.000613263,"percentage":48.2621},"jitterMean":{"lesser":0.0159995,"mean":0.0160003,"upper":0.016001,"percentage":0.0090746},"jitterVariance":{"lesser":1.89356e-10,"mean":3.05303e-10,"upper":4.21251e-10,"percentage":75.9555}}},{"t1":0,"w1":0,"x1":0,"nq1":10787.5,"t2":0.000284099,"w2":2.80992e-05,"x2":0.000256,"nq2":0.000733071,"jitterE":0.0159973,"jitterV":8.72429e-10,"confidenceInterval":{"t1":{"lesser":0,"mean":0,"upper":0,"percentage":0},"w1":{"lesser":0,"mean":0,"upper":0,"percentage":0},"x1":{"lesser":0,"mean":0,"upper":0,"percentage":0},"nq1":{"lesser":10581,"mean":10617.1,"upper":10653.1,"percentage":0.679273},"t2":{"lesser":0.000274302,"mean":0.000279045,"upper":0.000283787,"percentage":3.39891},"w2":{"lesser":1.83024e-05,"mean":2.30446e-05,"upper":2.77869e-05,"percentage":41.1569},"nq2":{"lesser":0.000387394,"mean":0.000502898,"upper":0.000618402,"percentage":45.9354},"jitterMean":{"lesser":0.0159994,"mean":0.0160002,"upper":0.0160009,"percentage":0.00903033},"jitterVariance":{"lesser":2.0933e-10,"mean":3.26308e-10,"upper":4.43286e-10,"percentage":71.6977}}},{"t1":0,"w1":0,"x1":0,"nq1":10791.2,"t2":0.000266785,"w2":1.07855e-05,"x2":0.000256,"nq2":0.000298876,"jitterE":0.016,"jitterV":-4.84109e-19,"confidenceInterval":{"t1":{"lesser":0,"mean":0,"upper":0,"percentage":0},"w1":{"lesser":0,"mean":0,"upper":0,"percentage":0},"x1":{"lesser":0,"mean":0,"upper":0,"percentage":0},"nq1":{"lesser":10587,"mean":10623.3,"upper":10659.6,"percentage":0.683073},"t2":{"lesser":0.000273982,"mean":0.000278607,"upper":0.000283232,"percentage":3.31989},"w2":{"lesser":1.79821e-05,"mean":2.26068e-05,"upper":2.72315e-05,"percentage":40.9144},"nq2":{"lesser":0.000383751,"mean":0.000495611,"upper":0.000607472,"percentage":45.1405},"jitterMean":{"lesser":0.0159995,"mean":0.0160002,"upper":0.0160008,"percentage":0.00869246},"jitterVariance":{"lesser":2.00332e-10,"mean":3.14654e-10,"upper":4.28976e-10,"percentage":72.6651}}},{"t1":0,"w1":0,"x1":0,"nq1":10801.8,"t2":0.000259153,"w2":3.15293e-06,"x2":0.000256,"nq2":7.65114e-05,"jitterE":0.0159983,"jitterV":2.42707e-10,"confidenceInterval":{"t1":{"lesser":0,"mean":0,"upper":0,"percentage":0},"w1":{"lesser":0,"mean":0,"upper":0,"percentage":0},"x1":{"lesser":0,"mean":0,"upper":0,"percentage":0},"nq1":{"lesser":10604.3,"mean":10629.5,"upper":10654.6,"percentage":0.47288},"t2":{"lesser":0.000274768,"mean":0.000277936,"upper":0.000281104,"percentage":2.27956},"w2":{"lesser":1.87681e-05,"mean":2.1936e-05,"upper":2.51038e-05,"percentage":28.8828},"nq2":{"lesser":0.000405024,"mean":0.00048116,"upper":0.000557295,"percentage":31.6466},"jitterMean":{"lesser":0.0159996,"mean":0.0160001,"upper":0.0160006,"percentage":0.00584629},"jitterVariance":{"lesser":2.3625e-10,"mean":3.12173e-10,"upper":3.88096e-10,"percentage":48.6417}}},{"t1":0,"w1":0,"x1":0,"nq1":10817.3,"t2":0.000256922,"w2":9.22449e-07,"x2":0.000256,"nq2":0,"jitterE":0.016,"jitterV":-4.59806e-19,"confidenceInterval":{"t1":{"lesser":0,"mean":0,"upper":0,"percentage":0},"w1":{"lesser":0,"mean":0,"upper":0,"percentage":0},"x1":{"lesser":0,"mean":0,"upper":0,"percentage":0},"nq1":{"lesser":10600.1,"mean":10635.7,"upper":10671.4,"percentage":0.670585},"t2":{"lesser":0.000272781,"mean":0.000277236,"upper":0.00028169,"percentage":3.2138},"w2":{"lesser":1.67806e-05,"mean":2.12355e-05,"upper":2.56904e-05,"percentage":41.957},"nq2":{"lesser":0.000358385,"mean":0.000465121,"upper":0.000571857,"percentage":45.8961},"jitterMean":{"lesser":0.0159994,"mean":0.0160001,"upper":0.0160007,"percentage":0.00794197},"jitterVariance":{"lesser":1.97221e-10,"mean":3.01768e-10,"upper":4.06314e-10,"percentage":69.2896}}}],"average":{"t1":0,"w1":0,"x1":0,"nq1":319071,"t2":0.00831707,"w2":0.00806107,"x2":0.000256,"nq2":0.0139536,"jitterE":0.480003,"jitterV":9.05303e-09},"confidenceInterval":{"t1":{"lesser":0,"mean":0,"upper":0,"percentage":0},"w1":{"lesser":0,"mean":0,"upper":0,"percentage":0},"x1":{"lesser":0,"mean":0,"upper":0,"percentage":0},"nq1":{"lesser":10600.1,"mean":10635.7,"upper":10671.4,"percentage":0.670585},"t2":{"lesser":0.000272781,"mean":0.000277236,"upper":0.00028169,"percentage":3.2138},"w2":{"lesser":1.67806e-05,"mean":2.12355e-05,"upper":2.56904e-05,"percentage":41.957},"nq2":{"lesser":0.000358385,"mean":0.000465121,"upper":0.000571857,"percentage":45.8961},"jitterMean":{"lesser":0.0159994,"mean":0.0160001,"upper":0.0160007,"percentage":0.00794197},"jitterVariance":{"lesser":1.97221e-10,"mean":3.01768e-10,"upper":4.06314e-10,"percentage":69.2896}}}
