{"samples":10000,"simulations":[{"t1":0,"w1":0,"x1":0,"nq1":15464.2,"t2":0.000282381,"w2":2.63812e-05,"x2":0.000256,"nq2":0.000596949,"jitterE":0.0159999,"jitterV":6.57969e-10},{"t1":0,"w1":0,"x1":0,"nq1":17270.8,"t2":0.000282262,"w2":2.62623e-05,"x2":0.000256,"nq2":0.000574757,"jitterE":0.0160001,"jitterV":5.86262e-10,"confidenceInterval":{"t1":{"lesser":0,"mean":0,"upper":0,"percentage":0},"w1":{"lesser":0,"mean":0,"upper":0,"percentage":0},"x1":{"lesser":0,"mean":0,"upper":0,"percentage":0},"nq1":{"lesser":13729.8,"mean":16367.5,"upper":19005.1,"percentage":32.2303},"t2":{"lesser":0.000282148,"mean":0.000282322,"upper":0.000282495,"percentage":0.123035},"w2":{"lesser":2.61481e-05,"mean":2.63217e-05,"upper":2.64954e-05,"percentage":1.31965},"nq2":{"lesser":0.000553452,"mean":0.000585853,"upper":0.000618254,"percentage":11.0612},"jitterMean":{"lesser":0.0159997,"mean":0.016,"upper":0.0160004,"percentage":0.00412337},"jitterVariance":{"lesser":5.17423e-10,"mean":6.22115e-10,"upper":7.26808e-10,"percentage":33.657}}},{"t1":0,"w1":0,"x1":0,"nq1":19017.2,"t2":0.000283253,"w2":2.72533e-05,"x2":0.000256,"nq2":0.000602618,"jitterE":0.0159998,"jitterV":5.1224e-10,"confidenceInterval":{"t1":{"lesser":0,"mean":0,"upper":0,"percentage":0},"w1":{"lesser":0,"mean":0,"upper":0,"percentage":0},"x1":{"lesser":0,"mean":0,"upper":0,"percentage":0},"nq1":{"lesser":14837.2,"mean":17250.7,"upper":19664.2,"percentage":27.9818},"t2":{"lesser":0.000281897,"mean":0.000282632,"upper":0.000283367,"percentage":0.520186},"w2":{"lesser":2.58972e-05,"mean":2.66323e-05,"upper":2.73674e-05,"percentage":5.52042},"nq2":{"lesser":0.000571438,"mean":0.000591441,"upper":0.000611445,"percentage":6.76435},"jitterMean":{"lesser":0.0159997,"mean":0.016,"upper":0.0160002,"percentage":0.0028901},"jitterVariance":{"lesser":4.86499e-10,"mean":5.8549e-10,"upper":6.84481e-10,"percentage":33.8148}}},{"t1":0,"w1":0,"x1":0,"nq1":20813.1,"t2":0.000287926,"w2":3.19258e-05,"x2":0.000256,"nq2":0.000782362,"jitterE":0.0160001,"jitterV":6.80613e-10,"confidenceInterval":{"t1":{"lesser":0,"mean":0,"upper":0,"percentage":0},"w1":{"lesser":0,"mean":0,"upper":0,"percentage":0},"x1":{"lesser":0,"mean":0,"upper":0,"percentage":0},"nq1":{"lesser":15692.5,"mean":18141.3,"upper":20590.1,"percentage":26.9966},"t2":{"lesser":0.000281095,"mean":0.000283956,"upper":0.000286816,"percentage":2.01473},"w2":{"lesser":2.50952e-05,"mean":2.79556e-05,"upper":3.08161e-05,"percentage":20.4644},"nq2":{"lesser":0.000536607,"mean":0.000639172,"upper":0.000741736,"percentage":32.093},"jitterMean":{"lesser":0.0159998,"mean":0.016,"upper":0.0160001,"percentage":0.00197043},"jitterVariance":{"lesser":5.28074e-10,"mean":6.09271e-10,"upper":6.90468e-10,"percentage":26.654}}},{"t1":0,"w1":0,"x1":0,"nq1":22620,"t2":0.000279134,"w2":2.31342e-05,"x2":0.000256,"nq2":0.000495899,"jitterE":0.0159998,"jitterV":4.69568e-10,"confidenceInterval":{"t1":{"lesser":0,"mean":0,"upper":0,"percentage":0},"w1":{"lesser":0,"mean":0,"upper":0,"percentage":0},"x1":{"lesser":0,"mean":0,"upper":0,"percentage":0},"nq1":{"lesser":16493.1,"mean":19037,"upper":21580.9,"percentage":26.7259},"t2":{"lesser":0.000280135,"mean":0.000282991,"upper":0.000285848,"percentage":2.01893},"w2":{"lesser":2.41347e-05,"mean":2.69914e-05,"upper":2.9848e-05,"percentage":21.1675},"nq2":{"lesser":0.000515798,"mean":0.000610517,"upper":0.000705236,"percentage":31.0292},"jitterMean":{"lesser":0.0159998,"mean":0.0159999,"upper":0.0160001,"percentage":0.00174681},"jitterVariance":{"lesser":4.99457e-10,"mean":5.8133e-10,"upper":6.63204e-10,"percentage":28.1676}}},{"t1":0,"w1":0,"x1":0,"nq1":24344,"t2":0.000277519,"w2":2.15194e-05,"x2":0.000256,"nq2":0.000441687,"jitterE":0.016,"jitterV":5.13147e-10,"confidenceInterval":{"t1":{"lesser":0,"mean":0,"upper":0,"percentage":0},"w1":{"lesser":0,"mean":0,"upper":0,"percentage":0},"x1":{"lesser":0,"mean":0,"upper":0,"percentage":0},"nq1":{"lesser":17282.4,"mean":19921.5,"upper":22560.7,"percentage":26.4952},"t2":{"lesser":0.000279216,"mean":0.000282079,"upper":0.000284943,"percentage":2.03015},"w2":{"lesser":2.3216e-05,"mean":2.60794e-05,"upper":2.89427e-05,"percentage":21.9585},"nq2":{"lesser":0.00048991,"mean":0.000582379,"upper":0.000674848,"percentage":31.7555},"jitterMean":{"lesser":0.0159998,"mean":0.016,"upper":0.0160001,"percentage":0.00140751},"jitterVariance":{"lesser":5.01829e-10,"mean":5.69966e-10,"upper":6.38104e-10,"percentage":23.9093}}},{"t1":0,"w1":0,"x1":0,"nq1":26150.5,"t2":0.000281164,"w2":2.51644e-05,"x2":0.000256,"nq2":0.000527146,"jitterE":0.0159998,"jitterV":4.64403e-10,"confidenceInterval":{"t1":{"lesser":0,"mean":0,"upper":0,"percentage":0},"w1":{"lesser":0,"mean":0,"upper":0,"percentage":0},"x1":{"lesser":0,"mean":0,"upper":0,"percentage":0},"nq1":{"lesser":18059,"mean":20811.4,"upper":23563.8,"percentage":26.451},"t2":{"lesser":0.000279576,"mean":0.000281949,"upper":0.000284322,"percentage":1.68337},"w2":{"lesser":2.35755e-05,"mean":2.59487e-05,"upper":2.83218e-05,"percentage":18.2909},"nq2":{"lesser":0.000496816,"mean":0.000574488,"upper":0.000652161,"percentage":27.0406},"jitterMean":{"lesser":0.0159998,"mean":0.0159999,"upper":0.016,"percentage":0.00123025},"jitterVariance":{"lesser":4.91869e-10,"mean":5.54886e-10,"upper":6.17903e-10,"percentage":22.7133}}},{"t1":0,"w1":0,"x1":0,"nq1":27769.7,"t2":0.00027789,"w2":2.18905e-05,"x2":0.000256,"nq2":0.000471945,"jitterE":0.0159999,"jitterV":4.60251e-10,"confidenceInterval":{"t1":{"lesser":0,"mean":0,"upper":0,"percentage":0},"w1":{"lesser":0,"mean":0,"upper":0,"percentage":0},"x1":{"lesser":0,"mean":0,"upper":0,"percentage":0},"nq1":{"lesser":18836.7,"mean":21681.2,"upper":24525.7,"percentage":26.2393},"t2":{"lesser":0.000279214,"mean":0.000281441,"upper":0.000283668,"percentage":1.58256},"w2":{"lesser":2.32144e-05,"mean":2.54414e-05,"upper":2.76684e-05,"percentage":17.5068},"nq2":{"lesser":0.000491474,"mean":0.00056167,"upper":0.000631867,"percentage":24.9957},"jitterMean":{"lesser":0.0159998,"mean":0.0159999,"upper":0.016,"percentage":0.00105668},"jitterVariance":{"lesser":4.85148e-10,"mean":5.43057e-10,"upper":6.00965e-10,"percentage":21.327}}},{"t1":0,"w1":0,"x1":0,"nq1":29609.1,"t2":0.000287778,"w2":3.1778e-05,"x2":0.000256,"nq2":0.000695655,"jitterE":0.0160003,"jitterV":4.66308e-10,"confidenceInterval":{"t1":{"lesser":0,"mean":0,"upper":0,"percentage":0},"w1":{"lesser":0,"mean":0,"upper":0,"percentage":0},"x1":{"lesser":0,"mean":0,"upper":0,"percentage":0},"nq1":{"lesser":19609.3,"mean":22562.1,"upper":25514.8,"percentage":26.1746},"t2":{"lesser":0.000279819,"mean":0.000282145,"upper":0.000284472,"percentage":1.64902},"w2":{"lesser":2.38191e-05,"mean":2.61454e-05,"upper":2.84718e-05,"percentage":17.7952},"nq2":{"lesser":0.000509724,"mean":0.000576558,"upper":0.000643391,"percentage":23.1837},"jitterMean":{"lesser":0.0159999,"mean":0.016,"upper":0.0160001,"percentage":0.00126562},"jitterVariance":{"lesser":4.81828e-10,"mean":5.34529e-10,"upper":5.8723e-10,"percentage":19.7186}}},{"t1":0,"w1":0,"x1":0,"nq1":31348.6,"t2":0.000279823,"w2":2.38231e-05,"x2":0.000256,"nq2":0.000517467,"jitterE":0.0159997,"jitterV":4.82906e-10,"confidenceInterval":{"t1":{"lesser":0,"mean":0,"upper":0,"percentage":0},"w1":{"lesser":0,"mean":0,"upper":0,"percentage":0},"x1":{"lesser":0,"mean":0,"upper":0,"percentage":0},"nq1":{"lesser":20382.8,"mean":23440.7,"upper":26498.7,"percentage":26.0909},"t2":{"lesser":0.000279814,"mean":0.000281913,"upper":0.000284013,"percentage":1.48945},"w2":{"lesser":2.38137e-05,"mean":2.59132e-05,"upper":2.80127e-05,"percentage":16.204},"nq2":{"lesser":0.000510593,"mean":0.000570649,"upper":0.000630704,"percentage":21.0481},"jitterMean":{"lesser":0.0159998,"mean":0.0159999,"upper":0.016,"percentage":0.00122755},"jitterVariance":{"lesser":4.8184e-10,"mean":5.29367e-10,"upper":5.76893e-10,"percentage":17.9561}}},{"t1":0,"w1":0,"x1":0,"nq1":33156.3,"t2":0.000273468,"w2":1.74678e-05,"x2":0.000256,"nq2":0.000364912,"jitterE":0.0160002,"jitterV":3.29499e-10,"confidenceInterval":{"t1":{"lesser":0,"mean":0,"upper":0,"percentage":0},"w1":{"lesser":0,"mean":0,"upper":0,"percentage":0},"x1":{"lesser":0,"mean":0,"upper":0,"percentage":0},"nq1":{"lesser":21156.5,"mean":24323.9,"upper":27491.4,"percentage":26.0438},"t2":{"lesser":0.000278812,"mean":0.000281145,"upper":0.000283479,"percentage":1.65986},"w2":{"lesser":2.28121e-05,"mean":2.51454e-05,"upper":2.74788e-05,"percentage":18.5586},"nq2":{"lesser":0.000488484,"mean":0.000551945,"upper":0.000615407,"percentage":22.9956},"jitterMean":{"lesser":0.0159999,"mean":0.016,"upper":0.0160001,"percentage":0.00119185},"jitterVariance":{"lesser":4.57526e-10,"mean":5.11197e-10,"upper":5.64867e-10,"percentage":20.998}}},{"t1":0,"w1":0,"x1":0,"nq1":34960.7,"t2":0.000278041,"w2":2.20413e-05,"x2":0.000256,"nq2":0.000455238,"jitterE":0.0159999,"jitterV":4.43859e-10,"confidenceInterval":{"t1":{"lesser":0,"mean":0,"upper":0,"percentage":0},"w1":{"lesser":0,"mean":0,"upper":0,"percentage":0},"x1":{"lesser":0,"mean":0,"upper":0,"percentage":0},"nq1":{"lesser":21935.3,"mean":25210.3,"upper":28485.4,"percentage":25.9815},"t2":{"lesser":0.000278724,"mean":0.000280887,"upper":0.00028305,"percentage":1.54019},"w2":{"lesser":2.27237e-05,"mean":2.48868e-05,"upper":2.70499e-05,"percentage":17.3835},"nq2":{"lesser":0.000484639,"mean":0.000543886,"upper":0.000603134,"percentage":21.7867},"jitterMean":{"lesser":0.0159999,"mean":0.016,"upper":0.016,"percentage":0.00109502},"jitterVariance":{"lesser":4.55955e-10,"mean":5.05585e-10,"upper":5.55215e-10,"percentage":19.6327}}},{"t1":0,"w1":0,"x1":0,"nq1":36772.6,"t2":0.000282614,"w2":2.66141e-05,"x2":0.000256,"nq2":0.000607535,"jitterE":0.0160002,"jitterV":4.21719e-10,"confidenceInterval":{"t1":{"lesser":0,"mean":0,"upper":0,"percentage":0},"w1":{"lesser":0,"mean":0,"upper":0,"percentage":0},"x1":{"lesser":0,"mean":0,"upper":0,"percentage":0},"nq1":{"lesser":22716.7,"mean":26099.7,"upper":29482.8,"percentage":25.9239},"t2":{"lesser":0.000279028,"mean":0.00028102,"upper":0.000283011,"percentage":1.41729},"w2":{"lesser":2.30282e-05,"mean":2.50196e-05,"upper":2.70111e-05,"percentage":15.919},"nq2":{"lesser":0.000493929,"mean":0.000548782,"upper":0.000603635,"percentage":19.9908},"jitterMean":{"lesser":0.0159999,"mean":0.016,"upper":0.0160001,"percentage":0.00106052},"jitterVariance":{"lesser":4.52346e-10,"mean":4.99134e-10,"upper":5.45922e-10,"percentage":18.7475}}},{"t1":0,"w1":0,"x1":0,"nq1":38518,"t2":0.000280784,"w2":2.47837e-05,"x2":0.000256,"nq2":0.000595802,"jitterE":0.0160001,"jitterV":5.31353e-10,"confidenceInterval":{"t1":{"lesser":0,"mean":0,"upper":0,"percentage":0},"w1":{"lesser":0,"mean":0,"upper":0,"percentage":0},"x1":{"lesser":0,"mean":0,"upper":0,"percentage":0},"nq1":{"lesser":23502.6,"mean":26986.8,"upper":30470.9,"percentage":25.8213},"t2":{"lesser":0.000279169,"mean":0.000281003,"upper":0.000282836,"percentage":1.305},"w2":{"lesser":2.31693e-05,"mean":2.50028e-05,"upper":2.68363e-05,"percentage":14.6667},"nq2":{"lesser":0.000501299,"mean":0.000552141,"upper":0.000602983,"percentage":18.4164},"jitterMean":{"lesser":0.0159999,"mean":0.016,"upper":0.0160001,"percentage":0.00100072},"jitterVariance":{"lesser":4.58173e-10,"mean":5.01435e-10,"upper":5.44698e-10,"percentage":17.2555}}},{"t1":0,"w1":0,"x1":0,"nq1":40303.8,"t2":0.000283608,"w2":2.76084e-05,"x2":0.000256,"nq2":0.000601277,"jitterE":0.0160003,"jitterV":5.51291e-10,"confidenceInterval":{"t1":{"lesser":0,"mean":0,"upper":0,"percentage":0},"w1":{"lesser":0,"mean":0,"upper":0,"percentage":0},"x1":{"lesser":0,"mean":0,"upper":0,"percentage":0},"nq1":{"lesser":24290.2,"mean":27874.6,"upper":31458.9,"percentage":25.7177},"t2":{"lesser":0.00027945,"mean":0.000281176,"upper":0.000282903,"percentage":1.22787},"w2":{"lesser":2.34502e-05,"mean":2.51765e-05,"upper":2.69027e-05,"percentage":13.7132},"nq2":{"lesser":0.000507951,"mean":0.000555417,"upper":0.000602882,"percentage":17.0918},"jitterMean":{"lesser":0.0159999,"mean":0.016,"upper":0.0160001,"percentage":0.00104457},"jitterVariance":{"lesser":4.64246e-10,"mean":5.04759e-10,"upper":5.45273e-10,"percentage":16.0526}}},{"t1":0,"w1":0,"x1":0,"nq1":42157.3,"t2":0.000286017,"w2":3.00173e-05,"x2":0.000256,"nq2":0.000692408,"jitterE":0.0160001,"jitterV":5.98547e-10,"confidenceInterval":{"t1":{"lesser":0,"mean":0,"upper":0,"percentage":0},"w1":{"lesser":0,"mean":0,"upper":0,"percentage":0},"x1":{"lesser":0,"mean":0,"upper":0,"percentage":0},"nq1":{"lesser":25082,"mean":28767.2,"upper":32452.5,"percentage":25.6214},"t2":{"lesser":0.000279786,"mean":0.000281479,"upper":0.000283172,"percentage":1.20282},"w2":{"lesser":2.37862e-05,"mean":2.5479e-05,"upper":2.71719e-05,"percentage":13.2881},"nq2":{"lesser":0.000517298,"mean":0.000563979,"upper":0.000610659,"percentage":16.5541},"jitterMean":{"lesser":0.0159999,"mean":0.016,"upper":0.0160001,"percentage":0.000986889},"jitterVariance":{"lesser":4.71512e-10,"mean":5.10621e-10,"upper":5.49729e-10,"percentage":15.318}}},{"t1":0,"w1":0,"x1":0,"nq1":44009.6,"t2":0.000279273,"w2":2.32732e-05,"x2":0.000256,"nq2":0.000495347,"jitterE":0.016,"jitterV":4.32061e-10,"confidenceInterval":{"t1":{"lesser":0,"mean":0,"upper":0,"percentage":0},"w1":{"lesser":0,"mean":0,"upper":0,"percentage":0},"x1":{"lesser":0,"mean":0,"upper":0,"percentage":0},"nq1":{"lesser":25877.7,"mean":29663.8,"upper":33450,"percentage":25.5272},"t2":{"lesser":0.000279749,"mean":0.000281349,"upper":0.00028295,"percentage":1.13786},"w2":{"lesser":2.37486e-05,"mean":2.53493e-05,"upper":2.695e-05,"percentage":12.629},"nq2":{"lesser":0.000515682,"mean":0.000559941,"upper":0.000604201,"percentage":15.8086},"jitterMean":{"lesser":0.0159999,"mean":0.016,"upper":0.0160001,"percentage":0.000923978},"jitterVariance":{"lesser":4.68517e-10,"mean":5.06e-10,"upper":5.43482e-10,"percentage":14.8152}}},{"t1":0,"w1":0,"x1":0,"nq1":45766.8,"t2":0.000283074,"w2":2.70743e-05,"x2":0.000256,"nq2":0.000599648,"jitterE":0.0160001,"jitterV":6.48559e-10,"confidenceInterval":{"t1":{"lesser":0,"mean":0,"upper":0,"percentage":0},"w1":{"lesser":0,"mean":0,"upper":0,"percentage":0},"x1":{"lesser":0,"mean":0,"upper":0,"percentage":0},"nq1":{"lesser":26677.6,"mean":30558.4,"upper":34439.3,"percentage":25.3995},"t2":{"lesser":0.000279932,"mean":0.000281445,"upper":0.000282958,"percentage":1.07523},"w2":{"lesser":2.3932e-05,"mean":2.54451e-05,"upper":2.69582e-05,"percentage":11.8929},"nq2":{"lesser":0.000520388,"mean":0.000562147,"upper":0.000603907,"percentage":14.8572},"jitterMean":{"lesser":0.0159999,"mean":0.016,"upper":0.0160001,"percentage":0.000870989},"jitterVariance":{"lesser":4.7612e-10,"mean":5.1392e-10,"upper":5.5172e-10,"percentage":14.7104}}},{"t1":0,"w1":0,"x1":0,"nq1":47560.2,"t2":0.000279946,"w2":2.39459e-05,"x2":0.000256,"nq2":0.00051318,"jitterE":0.0160002,"jitterV":4.25699e-10,"confidenceInterval":{"t1":{"lesser":0,"mean":0,"upper":0,"percentage":0},"w1":{"lesser":0,"mean":0,"upper":0,"percentage":0},"x1":{"lesser":0,"mean":0,"upper":0,"percentage":0},"nq1":{"lesser":27479.4,"mean":31453.3,"upper":35427.2,"percentage":25.2685},"t2":{"lesser":0.000279933,"mean":0.000281366,"upper":0.0002828,"percentage":1.01904},"w2":{"lesser":2.39326e-05,"mean":2.53662e-05,"upper":2.67998e-05,"percentage":11.3034},"nq2":{"lesser":0.000519932,"mean":0.00055957,"upper":0.000599208,"percentage":14.1673},"jitterMean":{"lesser":0.016,"mean":0.016,"upper":0.0160001,"percentage":0.000850365},"jitterVariance":{"lesser":4.72732e-10,"mean":5.09276e-10,"upper":5.45821e-10,"percentage":14.3516}}},{"t1":0,"w1":0,"x1":0,"nq1":49447.3,"t2":0.000273717,"w2":1.77168e-05,"x2":0.000256,"nq2":0.000365196,"jitterE":0.016,"jitterV":3.46552e-10,"confidenceInterval":{"t1":{"lesser":0,"mean":0,"upper":0,"percentage":0},"w1":{"lesser":0,"mean":0,"upper":0,"percentage":0},"x1":{"lesser":0,"mean":0,"upper":0,"percentage":0},"nq1":{"lesser":28284.1,"mean":32353,"upper":36421.8,"percentage":25.1529},"t2":{"lesser":0.000279475,"mean":0.000280984,"upper":0.000282493,"percentage":1.07394},"w2":{"lesser":2.34749e-05,"mean":2.49837e-05,"upper":2.64925e-05,"percentage":12.0782},"nq2":{"lesser":0.000508759,"mean":0.000549851,"upper":0.000590944,"percentage":14.9467},"jitterMean":{"lesser":0.016,"mean":0.016,"upper":0.0160001,"percentage":0.000805251},"jitterVariance":{"lesser":4.63812e-10,"mean":5.0114e-10,"upper":5.38468e-10,"percentage":14.8973}}},{"t1":0,"w1":0,"x1":0,"nq1":51337.1,"t2":0.000276755,"w2":2.07552e-05,"x2":0.000256,"nq2":0.000428096,"jitterE":0.016,"jitterV":4.35574e-10,"confidenceInterval":{"t1":{"lesser":0,"mean":0,"upper":0,"percentage":0},"w1":{"lesser":0,"mean":0,"upper":0,"percentage":0},"x1":{"lesser":0,"mean":0,"upper":0,"percentage":0},"nq1":{"lesser":29094.1,"mean":33257,"upper":37419.9,"percentage":25.0349},"t2":{"lesser":0.000279309,"mean":0.000280782,"upper":0.000282256,"percentage":1.04933},"w2":{"lesser":2.33092e-05,"mean":2.47824e-05,"upper":2.62555e-05,"percentage":11.8888},"nq2":{"lesser":0.000503801,"mean":0.000544054,"upper":0.000584306,"percentage":14.7972},"jitterMean":{"lesser":0.016,"mean":0.016,"upper":0.0160001,"percentage":0.000764607},"jitterVariance":{"lesser":4.62189e-10,"mean":4.98018e-10,"upper":5.33847e-10,"percentage":14.3886}}},{"t1":0,"w1":0,"x1":0,"nq1":53178.5,"t2":0.000278442,"w2":2.24425e-05,"x2":0.000256,"nq2":0.000507226,"jitterE":0.0160002,"jitterV":5.35304e-10,"confidenceInterval":{"t1":{"lesser":0,"mean":0,"upper":0,"percentage":0},"w1":{"lesser":0,"mean":0,"upper":0,"percentage":0},"x1":{"lesser":0,"mean":0,"upper":0,"percentage":0},"nq1":{"lesser":29908.3,"mean":34162.5,"upper":38416.8,"percentage":24.906},"t2":{"lesser":0.000279263,"mean":0.000280676,"upper":0.000282089,"percentage":1.00699},"w2":{"lesser":2.32628e-05,"mean":2.4676e-05,"upper":2.60892e-05,"percentage":11.454},"nq2":{"lesser":0.000503982,"mean":0.00054238,"upper":0.000580777,"percentage":14.159},"jitterMean":{"lesser":0.016,"mean":0.016,"upper":0.0160001,"percentage":0.000742252},"jitterVariance":{"lesser":4.65507e-10,"mean":4.99713e-10,"upper":5.33919e-10,"percentage":13.6904}}},{"t1":0,"w1":0,"x1":0,"nq1":54999.1,"t2":0.000277451,"w2":2.14513e-05,"x2":0.000256,"nq2":0.00048571,"jitterE":0.0160001,"jitterV":4.38251e-10,"confidenceInterval":{"t1":{"lesser":0,"mean":0,"upper":0,"percentage":0},"w1":{"lesser":0,"mean":0,"upper":0,"percentage":0},"x1":{"lesser":0,"mean":0,"upper":0,"percentage":0},"nq1":{"lesser":30723.5,"mean":35068.4,"upper":39413.4,"percentage":24.7796},"t2":{"lesser":0.000279167,"mean":0.000280536,"upper":0.000281905,"percentage":0.976165},"w2":{"lesser":2.31666e-05,"mean":2.45358e-05,"upper":2.59051e-05,"percentage":11.1612},"nq2":{"lesser":0.000503047,"mean":0.000539916,"upper":0.000576784,"percentage":13.6572},"jitterMean":{"lesser":0.016,"mean":0.016,"upper":0.0160001,"percentage":0.000715036},"jitterVariance":{"lesser":4.64093e-10,"mean":4.97041e-10,"upper":5.29989e-10,"percentage":13.2577}}},{"t1":0,"w1":0,"x1":0,"nq1":56682.1,"t2":0.000283004,"w2":2.70037e-05,"x2":0.000256,"nq2":0.000569298,"jitterE":0.0160001,"jitterV":4.57702e-10,"confidenceInterval":{"t1":{"lesser":0,"mean":0,"upper":0,"percentage":0},"w1":{"lesser":0,"mean":0,"upper":0,"percentage":0},"x1":{"lesser":0,"mean":0,"upper":0,"percentage":0},"nq1":{"lesser":31539.7,"mean":35969,"upper":40398.3,"percentage":24.6285},"t2":{"lesser":0.000279318,"mean":0.000280639,"upper":0.000281959,"percentage":0.94102},"w2":{"lesser":2.33182e-05,"mean":2.46386e-05,"upper":2.59591e-05,"percentage":10.7184},"nq2":{"lesser":0.00050584,"mean":0.00054114,"upper":0.00057644,"percentage":13.0464},"jitterMean":{"lesser":0.016,"mean":0.016,"upper":0.0160001,"percentage":0.000687905},"jitterVariance":{"lesser":4.63787e-10,"mean":4.95401e-10,"upper":5.27016e-10,"percentage":12.7633}}},{"t1":0,"w1":0,"x1":0,"nq1":58397,"t2":0.000277965,"w2":2.19653e-05,"x2":0.000256,"nq2":0.000488241,"jitterE":0.0159997,"jitterV":5.88668e-10,"confidenceInterval":{"t1":{"lesser":0,"mean":0,"upper":0,"percentage":0},"w1":{"lesser":0,"mean":0,"upper":0,"percentage":0},"x1":{"lesser":0,"mean":0,"upper":0,"percentage":0},"nq1":{"lesser":32356.8,"mean":36866.1,"upper":41375.5,"percentage":24.4633},"t2":{"lesser":0.000279254,"mean":0.000280532,"upper":0.000281809,"percentage":0.910713},"w2":{"lesser":2.32543e-05,"mean":2.45317e-05,"upper":2.58091e-05,"percentage":10.4144},"nq2":{"lesser":0.000505032,"mean":0.000539024,"upper":0.000573015,"percentage":12.6122},"jitterMean":{"lesser":0.016,"mean":0.016,"upper":0.0160001,"percentage":0.000706214},"jitterVariance":{"lesser":4.68198e-10,"mean":4.99132e-10,"upper":5.30066e-10,"percentage":12.3951}}},{"t1":0,"w1":0,"x1":0,"nq1":60202.7,"t2":0.00027943,"w2":2.34304e-05,"x2":0.000256,"nq2":0.000503509,"jitterE":0.0160003,"jitterV":4.64693e-10,"confidenceInterval":{"t1":{"lesser":0,"mean":0,"upper":0,"percentage":0},"w1":{"lesser":0,"mean":0,"upper":0,"percentage":0},"x1":{"lesser":0,"mean":0,"upper":0,"percentage":0},"nq1":{"lesser":33173.4,"mean":37763.7,"upper":42354,"percentage":24.3105},"t2":{"lesser":0.000279261,"mean":0.000280489,"upper":0.000281717,"percentage":0.875609},"w2":{"lesser":2.32614e-05,"mean":2.44894e-05,"upper":2.57173e-05,"percentage":10.0288},"nq2":{"lesser":0.000504955,"mean":0.000537658,"upper":0.000570361,"percentage":12.1649},"jitterMean":{"lesser":0.016,"mean":0.016,"upper":0.0160001,"percentage":0.000710311},"jitterVariance":{"lesser":4.68036e-10,"mean":4.97808e-10,"upper":5.27579e-10,"percentage":11.961}}},{"t1":0,"w1":0,"x1":0,"nq1":61922.4,"t2":0.000284987,"w2":2.89867e-05,"x2":0.000256,"nq2":0.000640541,"jitterE":0.0159996,"jitterV":6.6843e-10,"confidenceInterval":{"t1":{"lesser":0,"mean":0,"upper":0,"percentage":0},"w1":{"lesser":0,"mean":0,"upper":0,"percentage":0},"x1":{"lesser":0,"mean":0,"upper":0,"percentage":0},"nq1":{"lesser":33993.4,"mean":38658.5,"upper":43323.6,"percentage":24.135},"t2":{"lesser":0.000279443,"mean":0.000280656,"upper":0.000281869,"percentage":0.864539},"w2":{"lesser":2.34427e-05,"mean":2.46559e-05,"upper":2.58691e-05,"percentage":9.84096},"nq2":{"lesser":0.000509392,"mean":0.000541469,"upper":0.000573545,"percentage":11.8479},"jitterMean":{"lesser":0.016,"mean":0.016,"upper":0.0160001,"percentage":0.000767195},"jitterVariance":{"lesser":4.73572e-10,"mean":5.04127e-10,"upper":5.34682e-10,"percentage":12.122}}},{"t1":0,"w1":0,"x1":0,"nq1":63686.5,"t2":0.000285204,"w2":2.92035e-05,"x2":0.000256,"nq2":0.000650317,"jitterE":0.016,"jitterV":5.50285e-10,"confidenceInterval":{"t1":{"lesser":0,"mean":0,"upper":0,"percentage":0},"w1":{"lesser":0,"mean":0,"upper":0,"percentage":0},"x1":{"lesser":0,"mean":0,"upper":0,"percentage":0},"nq1":{"lesser":34811.7,"mean":39552.3,"upper":44292.9,"percentage":23.9712},"t2":{"lesser":0.000279618,"mean":0.000280818,"upper":0.000282018,"percentage":0.85459},"w2":{"lesser":2.36184e-05,"mean":2.48183e-05,"upper":2.60183e-05,"percentage":9.66965},"nq2":{"lesser":0.000513783,"mean":0.000545356,"upper":0.000576929,"percentage":11.579},"jitterMean":{"lesser":0.016,"mean":0.016,"upper":0.0160001,"percentage":0.000740055},"jitterVariance":{"lesser":4.76233e-10,"mean":5.05775e-10,"upper":5.35318e-10,"percentage":11.6821}}},{"t1":0,"w1":0,"x1":0,"nq1":65353.7,"t2":0.00027783,"w2":2.18305e-05,"x2":0.000256,"nq2":0.000497265,"jitterE":0.016,"jitterV":4.69469e-10,"confidenceInterval":{"t1":{"lesser":0,"mean":0,"upper":0,"percentage":0},"w1":{"lesser":0,"mean":0,"upper":0,"percentage":0},"x1":{"lesser":0,"mean":0,"upper":0,"percentage":0},"nq1":{"lesser":37128.3,"mean":40442,"upper":43755.7,"percentage":16.3875},"t2":{"lesser":0.00027991,"mean":0.000280715,"upper":0.000281521,"percentage":0.573804},"w2":{"lesser":2.39099e-05,"mean":2.47153e-05,"upper":2.55207e-05,"percentage":6.51724},"nq2":{"lesser":0.000522655,"mean":0.000543698,"upper":0.00056474,"percentage":7.7406},"jitterMean":{"lesser":0.016,"mean":0.016,"upper":0.0160001,"percentage":0.000491173},"jitterVariance":{"lesser":4.84863e-10,"mean":5.04523e-10,"upper":5.24183e-10,"percentage":7.79349}}},{"t1":0,"w1":0,"x1":0,"nq1":67198.5,"t2":0.000288179,"w2":3.21791e-05,"x2":0.000256,"nq2":0.000761758,"jitterE":0.0160002,"jitterV":4.89848e-10,"confidenceInterval":{"t1":{"lesser":0,"mean":0,"upper":0,"percentage":0},"w1":{"lesser":0,"mean":0,"upper":0,"percentage":0},"x1":{"lesser":0,"mean":0,"upper":0,"percentage":0},"nq1":{"lesser":36599.4,"mean":41333.9,"upper":46068.4,"percentage":22.9085},"t2":{"lesser":0.000279796,"mean":0.000280964,"upper":0.000282132,"percentage":0.831486},"w2":{"lesser":2.3796e-05,"mean":2.49641e-05,"upper":2.61322e-05,"percentage":9.35814},"nq2":{"lesser":0.000519981,"mean":0.000550966,"upper":0.000581951,"percentage":11.2475},"jitterMean":{"lesser":0.016,"mean":0.016,"upper":0.0160001,"percentage":0.00067335},"jitterVariance":{"lesser":4.77315e-10,"mean":5.04034e-10,"upper":5.30753e-10,"percentage":10.602}}}],"average":{"t1":0,"w1":0,"x1":0,"nq1":1.24002e+06,"t2":0.00842892,"w2":0.00817292,"x2":0.000256,"nq2":0.016529,"jitterE":0.480001,"jitterV":1.5121e-08},"confidenceInterval":{"t1":{"lesser":0,"mean":0,"upper":0,"percentage":0},"w1":{"lesser":0,"mean":0,"upper":0,"percentage":0},"x1":{"lesser":0,"mean":0,"upper":0,"percentage":0},"nq1":{"lesser":36599.4,"mean":41333.9,"upper":46068.4,"percentage":22.9085},"t2":{"lesser":0.000279796,"mean":0.000280964,"upper":0.000282132,"percentage":0.831486},"w2":{"lesser":2.3796e-05,"mean":2.49641e-05,"upper":2.61322e-05,"percentage":9.35814},"nq2":{"lesser":0.000519981,"mean":0.000550966,"upper":0.000581951,"percentage":11.2475},"jitterMean":{"lesser":0.016,"mean":0.016,"upper":0.0160001,"percentage":0.00067335},"jitterVariance":{"lesser":4.77315e-10,"mean":5.04034e-10,"upper":5.30753e-10,"percentage":10.602}}}
